Workbook

Sheet Overview
A1: Telecom Customer Segmentation - RFM Analysis
A2: Built from customers, recharges, plans, subscriptions, data usage & call records CSVs. All KPIs are live formulas.
B3: Key metrics | E3: Workbook guide
B4: Analysis date | C4: =RFM_Method!C5 -> 46054 | E4: =HYPERLINK("#'RFM_Method'!A1","RFM_Method") -> RFM_Method | F4: Parameters, metric definitions, scoring thresholds, segment matrix, process steps.
B5: Total customers | C5: =COUNTA(Raw_Customers!A2:A2001) -> 2000 | E5: =HYPERLINK("#'RFM_Calculation'!A1","RFM_Calculation") -> RFM_Calculation | F5: Per-customer Recency, Frequency, Monetary, scores, segment + usage enrichment.
B6: Customers with ≥1 recharge | C6: =COUNTIF(RFM_Calculation!I5:I2004,">0") -> 1533 | E6: =HYPERLINK("#'Segment_Summary'!A1","Segment_Summary") -> Segment_Summary | F6: Segment KPIs, score distribution, circle x segment heatmap, charts.
B7: Customers never recharged | C7: =COUNTIF(RFM_Calculation!I5:I2004,0) -> 467 | E7: =HYPERLINK("#'Marketing_Strategy'!A1","Marketing_Strategy") -> Marketing_Strategy | F7: Objective, offer, plans, channels, messaging, timing, KPIs & budget per segment.
B8: Total recharges | C8: =RFM_Method!C7 -> 3000 | E8: =HYPERLINK("#'Ad_Prompts'!A1","Ad_Prompts") -> Ad_Prompts | F8: 24 ready-to-use image-generation prompts with headline/copy/CTA per segment.
B9: Total recharge revenue | C9: =RFM_Method!C8 -> 2199245 | E9: =HYPERLINK("#'Raw_Customers'!A1","Raw_Customers") -> Raw_Customers | F9: customers.csv
B10: Avg revenue per recharging customer | C10: =C9/C6 -> 1434.6021 | E10: =HYPERLINK("#'Raw_Recharges'!A1","Raw_Recharges") -> Raw_Recharges | F10: recharges.csv (primary RFM source)
B11: Champions + Loyal share of revenue | C11: =SUMPRODUCT((Segment_Summary!A5:A16="Champions")+(Segment_Summary!A5:A16="Loyal Customers"),Segment_Summary!J5:J16) -> 0.50239923 | E11: =HYPERLINK("#'Raw_Plans'!A1","Raw_Plans") -> Raw_Plans | F11: plans.csv
B12: Revenue at risk (At Risk + Can't Lose Them) | C12: =SUMIF(Segment_Summary!A5:A16,"At Risk",Segment_Summary!I5:I16)+SUMIF(Segment_Summary!A5:A16,"Can't Lose Them",Segment_Summary!I5:I16) -> 461473 | E12: =HYPERLINK("#'Raw_Subscriptions'!A1","Raw_Subscriptions") -> Raw_Subscriptions | F12: subscriptions.csv
E13: =HYPERLINK("#'Raw_DataUsage'!A1","Raw_DataUsage") -> Raw_DataUsage | F13: data_usage.csv
E14: =HYPERLINK("#'Raw_Calls'!A1","Raw_Calls") -> Raw_Calls | F14: call_records.csv
B16: Colour legend
B17: Blue text = editable input
B18: Black text = formula
B19: Green text = link to another sheet
B21: Note: open in Microsoft Excel 2019/365 (uses MAXIFS). Formulas recalculate automatically on open.

Sheet RFM_Method
A1: RFM Calculation Method
A2: How Recency, Frequency and Monetary scores and segments are derived. Blue = editable input; black = formula.
B4: 1. Parameters
B5: Analysis (snapshot) date | C5: =INT(MAX(Raw_Recharges!$D$2:$D$3001))+1 -> 46054 | D5: Day after the latest recharge in the data. Recency = this date minus last recharge date.
B6: Observation window start | C6: =INT(MIN(Raw_Recharges!$D$2:$D$3001)) -> 45688 | D6: Earliest recharge in data.
B7: Total recharge transactions | C7: =COUNTA(Raw_Recharges!$A$2:$A$3001) -> 3000
B8: Total recharge revenue (₹) | C8: =SUM(Raw_Recharges!$E$2:$E$3001) -> 2199245
B10: 2. Metric definitions (per customer)
B11: Metric | C11: Definition | F11: Excel formula used (RFM_Calculation)
B12: Recency (R) | C12: Days between the analysis date and the customer's most recent recharge. Lower = better. | F12: fx: Analysis date - INT(MAXIFS(recharge_date, customer_id, ID))
B13: Frequency (F) | C13: Number of recharges made in the observation window. Higher = better. | F13: fx: COUNTIFS(customer_id, ID)
B14: Monetary (M) | C14: Total ₹ recharge amount in the window. Higher = better. | F14: fx: SUMIFS(amount, customer_id, ID)
B15: FM Score | C15: Average of F and M scores, rounded - combines engagement and value. | F15: fx: ROUND((F score + M score)/2, 0)
B16: RFM Cell | C16: Concatenated scores, e.g. 545 = R5 F4 M5. | F16: fx: R score & F score & M score
B17: Segment | C17: Looked up from the R x FM segment matrix below. | F17: fx: INDEX(Segment matrix, 6 - R score, FM score)
B19: 3. Scoring thresholds (1 = worst, 5 = best)
B20: Recency & Monetary use quintiles (20/40/60/80th percentiles) of recharging customers - recomputed automatically. Frequency uses fixed counts because most customers recharge 1-3 times (quintiles would tie).
B21: Percentile | C21: Recency cut-off (days) | D21: Monetary cut-off (₹) | E21: Frequency cut-off (#) | F21: Score | G21: Rule
B22: 0.2 | C22: =PERCENTILE(RFM_Calculation!$H$5:$H$2004,B22) -> 38 | D22: =PERCENTILE(RFM_Calculation!$J$5:$J$2004,B22) -> 398 | E22: 5 | F22: 5 | G22: R: days <= P20 -> 5 | M: ₹ >= P80 -> 5 | F: >= 5 recharges -> 5
B23: 0.4 | C23: =PERCENTILE(RFM_Calculation!$H$5:$H$2004,B23) -> 83 | D23: =PERCENTILE(RFM_Calculation!$J$5:$J$2004,B23) -> 666 | E23: 4 | F23: 4 | G23: R: days <= P40 -> 4 | M: ₹ >= P60 -> 4 | F: 4 recharges -> 4
B24: 0.6 | C24: =PERCENTILE(RFM_Calculation!$H$5:$H$2004,B24) -> 142 | D24: =PERCENTILE(RFM_Calculation!$J$5:$J$2004,B24) -> 1145 | E24: 3 | F24: 3 | G24: R: days <= P60 -> 3 | M: ₹ >= P40 -> 3 | F: 3 recharges -> 3
B25: 0.8 | C25: =PERCENTILE(RFM_Calculation!$H$5:$H$2004,B25) -> 231 | D25: =PERCENTILE(RFM_Calculation!$J$5:$J$2004,B25) -> 2999 | E25: 2 | F25: 2 | G25: R: days <= P80 -> 2 | M: ₹ >= P20 -> 2 | F: 2 recharges -> 2
E26: 1 | F26: 1 | G26: R: days > P80 -> 1 | M: ₹ < P20 -> 1 | F: 1 recharge -> 1
B28: Frequency cut-offs (yellow) are editable inputs. Percentiles (blue) are editable too.
B30: 4. Segment matrix (R score x FM score)
B31: R score \ FM score | C31: FM = 1 | D31: FM = 2 | E31: FM = 3 | F31: FM = 4 | G31: FM = 5
B32: R = 5 | C32: New Customers | D32: Promising | E32: Potential Loyalist | F32: Loyal Customers | G32: Champions
B33: R = 4 | C33: Promising | D33: Potential Loyalist | E33: Potential Loyalist | F33: Loyal Customers | G33: Champions
B34: R = 3 | C34: About to Sleep | D34: Need Attention | E34: Need Attention | F34: Loyal Customers | G34: Loyal Customers
B35: R = 2 | C35: Hibernating | D35: About to Sleep | E35: At Risk | F35: At Risk | G35: Can't Lose Them
B36: R = 1 | C36: Lost | D36: Hibernating | E36: At Risk | F36: Can't Lose Them | G36: Can't Lose Them
B37: Customers with zero recharges are assigned 'Never Recharged' (scores = 0) and excluded from the percentile cut-offs.
B39: 5. Process steps
B40: Step 1 | C40: Load raw recharge transactions (Raw_Recharges) and customer master (Raw_Customers).
B41: Step 2 | C41: Fix the analysis date = day after the last recharge in the dataset.
B42: Step 3 | C42: Per customer compute Last Recharge Date (MAXIFS), Recency days, Frequency (COUNTIFS) and Monetary (SUMIFS).
B43: Step 4 | C43: Compute quintile cut-offs for Recency and Monetary (PERCENTILE) and score 1-5; score Frequency on fixed counts.
B44: Step 5 | C44: Combine F and M into FM score; look up segment from the R x FM matrix.
B45: Step 6 | C45: Enrich with data usage (GB), call minutes and active-subscription flag for targeting.
B46: Step 7 | C46: Summarise by segment (Segment_Summary) and map each segment to a marketing play (Marketing_Strategy, Ad_Prompts).

Sheet RFM_Calculation
A1: RFM Calculation - per customer
A2: One row per customer (all 2,000). Green = link to raw sheet; black = formula. Filter / sort freely.
A4: Customer ID | B4: Name | C4: City | D4: Circle | E4: Status | F4: Join Date | G4: Last Recharge | H4: Recency (days) | I4: Frequency (#) | J4: Monetary (₹) | K4: R Score | L4: F Score | M4: M Score | N4: RFM Cell | O4: RFM Total | P4: FM Score | Q4: Segment | R4: Data Used Jan-26 (GB) | S4: Call Minutes | T4: Active Subscription
A5: =Raw_Customers!A2 -> C000001 | B5: =Raw_Customers!B2 -> Raj Yadav | C5: =Raw_Customers!E2 -> Mumbai | D5: =Raw_Customers!F2 -> Karnataka | E5: =Raw_Customers!H2 -> Active | F5: =Raw_Customers!G2 -> 45960 | G5: =IF(I5=0,"",INT(_xlfn.MAXIFS(Raw_Recharges!$D$2:$D$3001,Raw_Recharges!$B$2:$B$3001,A5))) -> 45838 | H5: =IF(I5=0,"",RFM_Method!$C$5-G5) -> 216 | I5: =COUNTIFS(Raw_Recharges!$B$2:$B$3001,A5) -> 2 | J5: =IF(I5=0,"",SUMIFS(Raw_Recharges!$E$2:$E$3001,Raw_Recharges!$B$2:$B$3001,A5)) -> 1298 | K5: =IF(I5=0,0,IF(H5<=RFM_Method!$C$22,5,IF(H5<=RFM_Method!$C$23,4,IF(H5<=RFM_Method!$C$24,3,IF(H5<=RFM_Method!$C$25,2,1))))) -> 2 | L5: =IF(I5=0,0,IF(I5>=RFM_Method!$E$22,5,IF(I5>=RFM_Method!$E$23,4,IF(I5>=RFM_Method!$E$24,3,IF(I5>=RFM_Method!$E$25,2,1))))) -> 2 | M5: =IF(I5=0,0,IF(J5>=RFM_Method!$D$25,5,IF(J5>=RFM_Method!$D$24,4,IF(J5>=RFM_Method!$D$23,3,IF(J5>=RFM_Method!$D$22,2,1))))) -> 4 | N5: =K5&L5&M5 -> 224 | O5: =K5+L5+M5 -> 8 | P5: =IF(I5=0,0,ROUND((L5+M5)/2,0)) -> 3 | Q5: =IF(I5=0,"Never Recharged",INDEX(RFM_Method!$C$32:$G$36,6-K5,P5)) -> At Risk | R5: =SUMIFS(Raw_DataUsage!$D$2:$D$5001,Raw_DataUsage!$B$2:$B$5001,A5)/1024 -> 3.9005371 | S5: =SUMIFS(Raw_Calls!$D$2:$D$5001,Raw_Calls!$B$2:$B$5001,A5)/60 -> 64.816667 | T5: =IF(COUNTIFS(Raw_Subscriptions!$B$2:$B$3001,A5,Raw_Subscriptions!$F$2:$F$3001,"Active")>0,"Yes","No") -> No
A6: =Raw_Customers!A3 -> C000002 | B6: =Raw_Customers!B3 -> Anita Sharma | C6: =Raw_Customers!E3 -> Pune | D6: =Raw_Customers!F3 -> West Bengal | E6: =Raw_Customers!H3 -> Active | F6: =Raw_Customers!G3 -> 44884 | G6: =IF(I6=0,"",INT(_xlfn.MAXIFS(Raw_Recharges!$D$2:$D$3001,Raw_Recharges!$B$2:$B$3001,A6))) | H6: =IF(I6=0,"",RFM_Method!$C$5-G6) | I6: =COUNTIFS(Raw_Recharges!$B$2:$B$3001,A6) -> 0 | J6: =IF(I6=0,"",SUMIFS(Raw_Recharges!$E$2:$E$3001,Raw_Recharges!$B$2:$B$3001,A6)) | K6: =IF(I6=0,0,IF(H6<=RFM_Method!$C$22,5,IF(H6<=RFM_Method!$C$23,4,IF(H6<=RFM_Method!$C$24,3,IF(H6<=RFM_Method!$C$25,2,1))))) -> 0 | L6: =IF(I6=0,0,IF(I6>=RFM_Method!$E$22,5,IF(I6>=RFM_Method!$E$23,4,IF(I6>=RFM_Method!$E$24,3,IF(I6>=RFM_Method!$E$25,2,1))))) -> 0 | M6: =IF(I6=0,0,IF(J6>=RFM_Method!$D$25,5,IF(J6>=RFM_Method!$D$24,4,IF(J6>=RFM_Method!$D$23,3,IF(J6>=RFM_Method!$D$22,2,1))))) -> 0 | N6: =K6&L6&M6 -> 000 | O6: =K6+L6+M6 -> 0 | P6: =IF(I6=0,0,ROUND((L6+M6)/2,0)) -> 0 | Q6: =IF(I6=0,"Never Recharged",INDEX(RFM_Method!$C$32:$G$36,6-K6,P6)) -> Never Recharged | R6: =SUMIFS(Raw_DataUsage!$D$2:$D$5001,Raw_DataUsage!$B$2:$B$5001,A6)/1024 -> 3.6974023 | S6: =SUMIFS(Raw_Calls!$D$2:$D$5001,Raw_Calls!$B$2:$B$5001,A6)/60 -> 39.5 | T6: =IF(COUNTIFS(Raw_Subscriptions!$B$2:$B$3001,A6,Raw_Subscriptions!$F$2:$F$3001,"Active")>0,"Yes","No") -> No
A7: =Raw_Customers!A4 -> C000003 | B7: =Raw_Customers!B4 -> Vikram Singh | C7: =Raw_Customers!E4 -> Hyderabad | D7: =Raw_Customers!F4 -> UP West | E7: =Raw_Customers!H4 -> Active | F7: =Raw_Customers!G4 -> 44226 | G7: =IF(I7=0,"",INT(_xlfn.MAXIFS(Raw_Recharges!$D$2:$D$3001,Raw_Recharges!$B$2:$B$3001,A7))) -> 45828 | H7: =IF(I7=0,"",RFM_Method!$C$5-G7) -> 226 | I7: =COUNTIFS(Raw_Recharges!$B$2:$B$3001,A7) -> 2 | J7: =IF(I7=0,"",SUMIFS(Raw_Recharges!$E$2:$E$3001,Raw_Recharges!$B$2:$B$3001,A7)) -> 1665 | K7: =IF(I7=0,0,IF(H7<=RFM_Method!$C$22,5,IF(H7<=RFM_Method!$C$23,4,IF(H7<=RFM_Method!$C$24,3,IF(H7<=RFM_Method!$C$25,2,1))))) -> 2 | L7: =IF(I7=0,0,IF(I7>=RFM_Method!$E$22,5,IF(I7>=RFM_Method!$E$23,4,IF(I7>=RFM_Method!$E$24,3,IF(I7>=RFM_Method!$E$25,2,1))))) -> 2 | M7: =IF(I7=0,0,IF(J7>=RFM_Method!$D$25,5,IF(J7>=RFM_Method!$D$24,4,IF(J7>=RFM_Method!$D$23,3,IF(J7>=RFM_Method!$D$22,2,1))))) -> 4 | N7: =K7&L7&M7 -> 224 | O7: =K7+L7+M7 -> 8 | P7: =IF(I7=0,0,ROUND((L7+M7)/2,0)) -> 3 | Q7: =IF(I7=0,"Never Recharged",INDEX(RFM_Method!$C$32:$G$36,6-K7,P7)) -> At Risk | R7: =SUMIFS(Raw_DataUsage!$D$2:$D$5001,Raw_DataUsage!$B$2:$B$5001,A7)/1024 -> 1.3238086 | S7: =SUMIFS(Raw_Calls!$D$2:$D$5001,Raw_Calls!$B$2:$B$5001,A7)/60 -> 67.666667 | T7: =IF(COUNTIFS(Raw_Subscriptions!$B$2:$B$3001,A7,Raw_Subscriptions!$F$2:$F$3001,"Active")>0,"Yes","No") -> Yes
A8: =Raw_Customers!A5 -> C000004 | B8: =Raw_Customers!B5 -> Anita Mishra | C8: =Raw_Customers!E5 -> Pune | D8: =Raw_Customers!F5 -> Punjab | E8: =Raw_Customers!H5 -> Active | F8: =Raw_Customers!G5 -> 45362 | G8: =IF(I8=0,"",INT(_xlfn.MAXIFS(Raw_Recharges!$D$2:$D$3001,Raw_Recharges!$B$2:$B$3001,A8))) -> 45847 | H8: =IF(I8=0,"",RFM_Method!$C$5-G8) -> 207 | I8: =COUNTIFS(Raw_Recharges!$B$2:$B$3001,A8) -> 2 | J8: =IF(I8=0,"",SUMIFS(Raw_Recharges!$E$2:$E$3001,Raw_Recharges!$B$2:$B$3001,A8)) -> 578 | K8: =IF(I8=0,0,IF(H8<=RFM_Method!$C$22,5,IF(H8<=RFM_Method!$C$23,4,IF(H8<=RFM_Method!$C$24,3,IF(H8<=RFM_Method!$C$25,2,1))))) -> 2 | L8: =IF(I8=0,0,IF(I8>=RFM_Method!$E$22,5,IF(I8>=RFM_Method!$E$23,4,IF(I8>=RFM_Method!$E$24,3,IF(I8>=RFM_Method!$E$25,2,1))))) -> 2 | M8: =IF(I8=0,0,IF(J8>=RFM_Method!$D$25,5,IF(J8>=RFM_Method!$D$24,4,IF(J8>=RFM_Method!$D$23,3,IF(J8>=RFM_Method!$D$22,2,1))))) -> 2 | N8: =K8&L8&M8 -> 222 | O8: =K8+L8+M8 -> 6 | P8: =IF(I8=0,0,ROUND((L8+M8)/2,0)) -> 2 | Q8: =IF(I8=0,"Never Recharged",INDEX(RFM_Method!$C$32:$G$36,6-K8,P8)) -> About to Sleep | R8: =SUMIFS(Raw_DataUsage!$D$2:$D$5001,Raw_DataUsage!$B$2:$B$5001,A8)/1024 -> 1.7641309 | S8: =SUMIFS(Raw_Calls!$D$2:$D$5001,Raw_Calls!$B$2:$B$5001,A8)/60 -> 49 | T8: =IF(COUNTIFS(Raw_Subscriptions!$B$2:$B$3001,A8,Raw_Subscriptions!$F$2:$F$3001,"Active")>0,"Yes","No") -> Yes
A9: =Raw_Customers!A6 -> C000005 | B9: =Raw_Customers!B6 -> Rahul Patel | C9: =Raw_Customers!E6 -> Chennai | D9: =Raw_Customers!F6 -> Gujarat | E9: =Raw_Customers!H6 -> Active | F9: =Raw_Customers!G6 -> 44616 | G9: =IF(I9=0,"",INT(_xlfn.MAXIFS(Raw_Recharges!$D$2:$D$3001,Raw_Recharges!$B$2:$B$3001,A9))) -> 45958 | H9: =IF(I9=0,"",RFM_Method!$C$5-G9) -> 96 | I9: =COUNTIFS(Raw_Recharges!$B$2:$B$3001,A9) -> 2 | J9: =IF(I9=0,"",SUMIFS(Raw_Recharges!$E$2:$E$3001,Raw_Recharges!$B$2:$B$3001,A9)) -> 627 | K9: =IF(I9=0,0,IF(H9<=RFM_Method!$C$22,5,IF(H9<=RFM_Method!$C$23,4,IF(H9<=RFM_Method!$C$24,3,IF(H9<=RFM_Method!$C$25,2,1))))) -> 3 | L9: =IF(I9=0,0,IF(I9>=RFM_Method!$E$22,5,IF(I9>=RFM_Method!$E$23,4,IF(I9>=RFM_Method!$E$24,3,IF(I9>=RFM_Method!$E$25,2,1))))) -> 2 | M9: =IF(I9=0,0,IF(J9>=RFM_Method!$D$25,5,IF(J9>=RFM_Method!$D$24,4,IF(J9>=RFM_Method!$D$23,3,IF(J9>=RFM_Method!$D$22,2,1))))) -> 2 | N9: =K9&L9&M9 -> 322 | O9: =K9+L9+M9 -> 7 | P9: =IF(I9=0,0,ROUND((L9+M9)/2,0)) -> 2 | Q9: =IF(I9=0,"Never Recharged",INDEX(RFM_Method!$C$32:$G$36,6-K9,P9)) -> Need Attention | R9: =SUMIFS(Raw_DataUsage!$D$2:$D$5001,Raw_DataUsage!$B$2:$B$5001,A9)/1024 -> 4.7704297 | S9: =SUMIFS(Raw_Calls!$D$2:$D$5001,Raw_Calls!$B$2:$B$5001,A9)/60 -> 28.2 | T9: =IF(COUNTIFS(Raw_Subscriptions!$B$2:$B$3001,A9,Raw_Subscriptions!$F$2:$F$3001,"Active")>0,"Yes","No") -> No
A10: =Raw_Customers!A7 -> C000006 | B10: =Raw_Customers!B7 -> Neha Mishra | C10: =Raw_Customers!E7 -> Bangalore | D10: =Raw_Customers!F7 -> Delhi NCR | E10: =Raw_Customers!H7 -> Inactive | F10: =Raw_Customers!G7 -> 45378 | G10: =IF(I10=0,"",INT(_xlfn.MAXIFS(Raw_Recharges!$D$2:$D$3001,Raw_Recharges!$B$2:$B$3001,A10))) -> 45941 | H10: =IF(I10=0,"",RFM_Method!$C$5-G10) -> 113 | I10: =COUNTIFS(Raw_Recharges!$B$2:$B$3001,A10) -> 3 | J10: =IF(I10=0,"",SUMIFS(Raw_Recharges!$E$2:$E$3001,Raw_Recharges!$B$2:$B$3001,A10)) -> 2144 | K10: =IF(I10=0,0,IF(H10<=RFM_Method!$C$22,5,IF(H10<=RFM_Method!$C$23,4,IF(H10<=RFM_Method!$C$24,3,IF(H10<=RFM_Method!$C$25,2,1))))) -> 3 | L10: =IF(I10=0,0,IF(I10>=RFM_Method!$E$22,5,IF(I10>=RFM_Method!$E$23,4,IF(I10>=RFM_Method!$E$24,3,IF(I10>=RFM_Method!$E$25,2,1))))) -> 3 | M10: =IF(I10=0,0,IF(J10>=RFM_Method!$D$25,5,IF(J10>=RFM_Method!$D$24,4,IF(J10>=RFM_Method!$D$23,3,IF(J10>=RFM_Method!$D$22,2,1))))) -> 4 | N10: =K10&L10&M10 -> 334 | O10: =K10+L10+M10 -> 10 | P10: =IF(I10=0,0,ROUND((L10+M10)/2,0)) -> 4 | Q10: =IF(I10=0,"Never Recharged",INDEX(RFM_Method!$C$32:$G$36,6-K10,P10)) -> Loyal Customers | R10: =SUMIFS(Raw_DataUsage!$D$2:$D$5001,Raw_DataUsage!$B$2:$B$5001,A10)/1024 -> 3.8248828 | S10: =SUMIFS(Raw_Calls!$D$2:$D$5001,Raw_Calls!$B$2:$B$5001,A10)/60 -> 38.5 | T10: =IF(COUNTIFS(Raw_Subscriptions!$B$2:$B$3001,A10,Raw_Subscriptions!$F$2:$F$3001,"Active")>0,"Yes","No") -> Yes
A11: =Raw_Customers!A8 -> C000007 | B11: =Raw_Customers!B8 -> Amit Jha | C11: =Raw_Customers!E8 -> Delhi | D11: =Raw_Customers!F8 -> Delhi NCR | E11: =Raw_Customers!H8 -> Active | F11: =Raw_Customers!G8 -> 44484 | G11: =IF(I11=0,"",INT(_xlfn.MAXIFS(Raw_Recharges!$D$2:$D$3001,Raw_Recharges!$B$2:$B$3001,A11))) -> 46028 | H11: =IF(I11=0,"",RFM_Method!$C$5-G11) -> 26 | I11: =COUNTIFS(Raw_Recharges!$B$2:$B$3001,A11) -> 1 | J11: =IF(I11=0,"",SUMIFS(Raw_Recharges!$E$2:$E$3001,Raw_Recharges!$B$2:$B$3001,A11)) -> 99 | K11: =IF(I11=0,0,IF(H11<=RFM_Method!$C$22,5,IF(H11<=RFM_Method!$C$23,4,IF(H11<=RFM_Method!$C$24,3,IF(H11<=RFM_Method!$C$25,2,1))))) -> 5 | L11: =IF(I11=0,0,IF(I11>=RFM_Method!$E$22,5,IF(I11>=RFM_Method!$E$23,4,IF(I11>=RFM_Method!$E$24,3,IF(I11>=RFM_Method!$E$25,2,1))))) -> 1 | M11: =IF(I11=0,0,IF(J11>=RFM_Method!$D$25,5,IF(J11>=RFM_Method!$D$24,4,IF(J11>=RFM_Method!$D$23,3,IF(J11>=RFM_Method!$D$22,2,1))))) -> 1 | N11: =K11&L11&M11 -> 511 | O11: =K11+L11+M11 -> 7 | P11: =IF(I11=0,0,ROUND((L11+M11)/2,0)) -> 1 | Q11: =IF(I11=0,"Never Recharged",INDEX(RFM_Method!$C$32:$G$36,6-K11,P11)) -> New Customers | R11: =SUMIFS(Raw_DataUsage!$D$2:$D$5001,Raw_DataUsage!$B$2:$B$5001,A11)/1024 -> 3.0334766 | S11: =SUMIFS(Raw_Calls!$D$2:$D$5001,Raw_Calls!$B$2:$B$5001,A11)/60 -> 39.9 | T11: =IF(COUNTIFS(Raw_Subscriptions!$B$2:$B$3001,A11,Raw_Subscriptions!$F$2:$F$3001,"Active")>0,"Yes","No") -> Yes
A12: =Raw_Customers!A9 -> C000008 | B12: =Raw_Customers!B9 -> Rahul Khan | C12: =Raw_Customers!E9 -> Bangalore | D12: =Raw_Customers!F9 -> UP East | E12: =Raw_Customers!H9 -> Active | F12: =Raw_Customers!G9 -> 44133 | G12: =IF(I12=0,"",INT(_xlfn.MAXIFS(Raw_Recharges!$D$2:$D$3001,Raw_Recharges!$B$2:$B$3001,A12))) | H12: =IF(I12=0,"",RFM_Method!$C$5-G12) | I12: =COUNTIFS(Raw_Recharges!$B$2:$B$3001,A12) -> 0 | J12: =IF(I12=0,"",SUMIFS(Raw_Recharges!$E$2:$E$3001,Raw_Recharges!$B$2:$B$3001,A12)) | K12: =IF(I12=0,0,IF(H12<=RFM_Method!$C$22,5,IF(H12<=RFM_Method!$C$23,4,IF(H12<=RFM_Method!$C$24,3,IF(H12<=RFM_Method!$C$25,2,1))))) -> 0 | L12: =IF(I12=0,0,IF(I12>=RFM_Method!$E$22,5,IF(I12>=RFM_Method!$E$23,4,IF(I12>=RFM_Method!$E$24,3,IF(I12>=RFM_Method!$E$25,2,1))))) -> 0 | M12: =IF(I12=0,0,IF(J12>=RFM_Method!$D$25,5,IF(J12>=RFM_Method!$D$24,4,IF(J12>=RFM_Method!$D$23,3,IF(J12>=RFM_Method!$D$22,2,1))))) -> 0 | N12: =K12&L12&M12 -> 000 | O12: =K12+L12+M12 -> 0 | P12: =IF(I12=0,0,ROUND((L12+M12)/2,0)) -> 0 | Q12: =IF(I12=0,"Never Recharged",INDEX(RFM_Method!$C$32:$G$36,6-K12,P12)) -> Never Recharged | R12: =SUMIFS(Raw_DataUsage!$D$2:$D$5001,Raw_DataUsage!$B$2:$B$5001,A12)/1024 -> 4.7340332 | S12: =SUMIFS(Raw_Calls!$D$2:$D$5001,Raw_Calls!$B$2:$B$5001,A12)/60 -> 19.216667 | T12: =IF(COUNTIFS(Raw_Subscriptions!$B$2:$B$3001,A12,Raw_Subscriptions!$F$2:$F$3001,"Active")>0,"Yes","No") -> No
A13: =Raw_Customers!A10 -> C000009 | B13: =Raw_Customers!B10 -> Simran Singh | C13: =Raw_Customers!E10 -> Mumbai | D13: =Raw_Customers!F10 -> UP East | E13: =Raw_Customers!H10 -> Inactive | F13: =Raw_Customers!G10 -> 45061 | G13: =IF(I13=0,"",INT(_xlfn.MAXIFS(Raw_Recharges!$D$2:$D$3001,Raw_Recharges!$B$2:$B$3001,A13))) -> 45964 | H13: =IF(I13=0,"",RFM_Method!$C$5-G13) -> 90 | I13: =COUNTIFS(Raw_Recharges!$B$2:$B$3001,A13) -> 3 | J13: =IF(I13=0,"",SUMIFS(Raw_Recharges!$E$2:$E$3001,Raw_Recharges!$B$2:$B$3001,A13)) -> 1494 | K13: =IF(I13=0,0,IF(H13<=RFM_Method!$C$22,5,IF(H13<=RFM_Method!$C$23,4,IF(H13<=RFM_Method!$C$24,3,IF(H13<=RFM_Method!$C$25,2,1))))) -> 3 | L13: =IF(I13=0,0,IF(I13>=RFM_Method!$E$22,5,IF(I13>=RFM_Method!$E$23,4,IF(I13>=RFM_Method!$E$24,3,IF(I13>=RFM_Method!$E$25,2,1))))) -> 3 | M13: =IF(I13=0,0,IF(J13>=RFM_Method!$D$25,5,IF(J13>=RFM_Method!$D$24,4,IF(J13>=RFM_Method!$D$23,3,IF(J13>=RFM_Method!$D$22,2,1))))) -> 4 | N13: =K13&L13&M13 -> 334 | O13: =K13+L13+M13 -> 10 | P13: =IF(I13=0,0,ROUND((L13+M13)/2,0)) -> 4 | Q13: =IF(I13=0,"Never Recharged",INDEX(RFM_Method!$C$32:$G$36,6-K13,P13)) -> Loyal Customers | R13: =SUMIFS(Raw_DataUsage!$D$2:$D$5001,Raw_DataUsage!$B$2:$B$5001,A13)/1024 -> 2.3053613 | S13: =SUMIFS(Raw_Calls!$D$2:$D$5001,Raw_Calls!$B$2:$B$5001,A13)/60 -> 169.03333 | T13: =IF(COUNTIFS(Raw_Subscriptions!$B$2:$B$3001,A13,Raw_Subscriptions!$F$2:$F$3001,"Active")>0,"Yes","No") -> No
A14: =Raw_Customers!A11 -> C000010 | B14: =Raw_Customers!B11 -> Raj Reddy | C14: =Raw_Customers!E11 -> Hyderabad | D14: =Raw_Customers!F11 -> Punjab | E14: =Raw_Customers!H11 -> Active | F14: =Raw_Customers!G11 -> 44285 | G14: =IF(I14=0,"",INT(_xlfn.MAXIFS(Raw_Recharges!$D$2:$D$3001,Raw_Recharges!$B$2:$B$3001,A14))) -> 46008 | H14: =IF(I14=0,"",RFM_Method!$C$5-G14) -> 46 | I14: =COUNTIFS(Raw_Recharges!$B$2:$B$3001,A14) -> 4 | J14: =IF(I14=0,"",SUMIFS(Raw_Recharges!$E$2:$E$3001,Raw_Recharges!$B$2:$B$3001,A14)) -> 1425 | K14: =IF(I14=0,0,IF(H14<=RFM_Method!$C$22,5,IF(H14<=RFM_Method!$C$23,4,IF(H14<=RFM_Method!$C$24,3,IF(H14<=RFM_Method!$C$25,2,1))))) -> 4 | L14: =IF(I14=0,0,IF(I14>=RFM_Method!$E$22,5,IF(I14>=RFM_Method!$E$23,4,IF(I14>=RFM_Method!$E$24,3,IF(I14>=RFM_Method!$E$25,2,1))))) -> 4 | M14: =IF(I14=0,0,IF(J14>=RFM_Method!$D$25,5,IF(J14>=RFM_Method!$D$24,4,IF(J14>=RFM_Method!$D$23,3,IF(J14>=RFM_Method!$D$22,2,1))))) -> 4 | N14: =K14&L14&M14 -> 444 | O14: =K14+L14+M14 -> 12 | P14: =IF(I14=0,0,ROUND((L14+M14)/2,0)) -> 4 | Q14: =IF(I14=0,"Never Recharged",INDEX(RFM_Method!$C$32:$G$36,6-K14,P14)) -> Loyal Customers | R14: =SUMIFS(Raw_DataUsage!$D$2:$D$5001,Raw_DataUsage!$B$2:$B$5001,A14)/1024 -> 7.8854492 | S14: =SUMIFS(Raw_Calls!$D$2:$D$5001,Raw_Calls!$B$2:$B$5001,A14)/60 -> 56.366667 | T14: =IF(COUNTIFS(Raw_Subscriptions!$B$2:$B$3001,A14,Raw_Subscriptions!$F$2:$F$3001,"Active")>0,"Yes","No") -> Yes
A15: =Raw_Customers!A12 -> C000011 | B15: =Raw_Customers!B12 -> Priya Jha | C15: =Raw_Customers!E12 -> Mumbai | D15: =Raw_Customers!F12 -> UP East | E15: =Raw_Customers!H12 -> Inactive | F15: =Raw_Customers!G12 -> 45669 | G15: =IF(I15=0,"",INT(_xlfn.MAXIFS(Raw_Recharges!$D$2:$D$3001,Raw_Recharges!$B$2:$B$3001,A15))) -> 46051 | H15: =IF(I15=0,"",RFM_Method!$C$5-G15) -> 3 | I15: =COUNTIFS(Raw_Recharges!$B$2:$B$3001,A15) -> 4 | J15: =IF(I15=0,"",SUMIFS(Raw_Recharges!$E$2:$E$3001,Raw_Recharges!$B$2:$B$3001,A15)) -> 1592 | K15: =IF(I15=0,0,IF(H15<=RFM_Method!$C$22,5,IF(H15<=RFM_Method!$C$23,4,IF(H15<=RFM_Method!$C$24,3,IF(H15<=RFM_Method!$C$25,2,1))))) -> 5 | L15: =IF(I15=0,0,IF(I15>=RFM_Method!$E$22,5,IF(I15>=RFM_Method!$E$23,4,IF(I15>=RFM_Method!$E$24,3,IF(I15>=RFM_Method!$E$25,2,1))))) -> 4 | M15: =IF(I15=0,0,IF(J15>=RFM_Method!$D$25,5,IF(J15>=RFM_Method!$D$24,4,IF(J15>=RFM_Method!$D$23,3,IF(J15>=RFM_Method!$D$22,2,1))))) -> 4 | N15: =K15&L15&M15 -> 544 | O15: =K15+L15+M15 -> 13 | P15: =IF(I15=0,0,ROUND((L15+M15)/2,0)) -> 4 | Q15: =IF(I15=0,"Never Recharged",INDEX(RFM_Method!$C$32:$G$36,6-K15,P15)) -> Loyal Customers | R15: =SUMIFS(Raw_DataUsage!$D$2:$D$5001,Raw_DataUsage!$B$2:$B$5001,A15)/1024 -> 4.1189648 | S15: =SUMIFS(Raw_Calls!$D$2:$D$5001,Raw_Calls!$B$2:$B$5001,A15)/60 -> 0 | T15: =IF(COUNTIFS(Raw_Subscriptions!$B$2:$B$3001,A15,Raw_Subscriptions!$F$2:$F$3001,"Active")>0,"Yes","No") -> Yes
A16: =Raw_Customers!A13 -> C000012 | B16: =Raw_Customers!B13 -> Pooja Yadav | C16: =Raw_Customers!E13 -> Pune | D16: =Raw_Customers!F13 -> Andhra Pradesh | E16: =Raw_Customers!H13 -> Active | F16: =Raw_Customers!G13 -> 44879 | G16: =IF(I16=0,"",INT(_xlfn.MAXIFS(Raw_Recharges!$D$2:$D$3001,Raw_Recharges!$B$2:$B$3001,A16))) -> 46024 | H16: =IF(I16=0,"",RFM_Method!$C$5-G16) -> 30 | I16: =COUNTIFS(Raw_Recharges!$B$2:$B$3001,A16) -> 3 | J16: =IF(I16=0,"",SUMIFS(Raw_Recharges!$E$2:$E$3001,Raw_Recharges!$B$2:$B$3001,A16)) -> 1163 | K16: =IF(I16=0,0,IF(H16<=RFM_Method!$C$22,5,IF(H16<=RFM_Method!$C$23,4,IF(H16<=RFM_Method!$C$24,3,IF(H16<=RFM_Method!$C$25,2,1))))) -> 5 | L16: =IF(I16=0,0,IF(I16>=RFM_Method!$E$22,5,IF(I16>=RFM_Method!$E$23,4,IF(I16>=RFM_Method!$E$24,3,IF(I16>=RFM_Method!$E$25,2,1))))) -> 3 | M16: =IF(I16=0,0,IF(J16>=RFM_Method!$D$25,5,IF(J16>=RFM_Method!$D$24,4,IF(J16>=RFM_Method!$D$23,3,IF(J16>=RFM_Method!$D$22,2,1))))) -> 4 | N16: =K16&L16&M16 -> 534 | O16: =K16+L16+M16 -> 12 | P16: =IF(I16=0,0,ROUND((L16+M16)/2,0)) -> 4 | Q16: =IF(I16=0,"Never Recharged",INDEX(RFM_Method!$C$32:$G$36,6-K16,P16)) -> Loyal Customers | R16: =SUMIFS(Raw_DataUsage!$D$2:$D$5001,Raw_DataUsage!$B$2:$B$5001,A16)/1024 -> 0.61993164 | S16: =SUMIFS(Raw_Calls!$D$2:$D$5001,Raw_Calls!$B$2:$B$5001,A16)/60 -> 84.516667 | T16: =IF(COUNTIFS(Raw_Subscriptions!$B$2:$B$3001,A16,Raw_Subscriptions!$F$2:$F$3001,"Active")>0,"Yes","No") -> Yes
... A2004: =Raw_Customers!A2001 -> C002000 | B2004: =Raw_Customers!B2001 -> Raj Gupta | C2004: =Raw_Customers!E2001 -> Bangalore | D2004: =Raw_Customers!F2001 -> Karnataka | E2004: =Raw_Customers!H2001 -> Active | F2004: =Raw_Customers!G2001 -> 45398 | G2004: =IF(I2004=0,"",INT(_xlfn.MAXIFS(Raw_Recharges!$D$2:$D$3001,Raw_Recharges!$B$2:$B$3001,A2004))) -> 45814 | H2004: =IF(I2004=0,"",RFM_Method!$C$5-G2004) -> 240 | I2004: =COUNTIFS(Raw_Recharges!$B$2:$B$3001,A2004) -> 1 | J2004: =IF(I2004=0,"",SUMIFS(Raw_Recharges!$E$2:$E$3001,Raw_Recharges!$B$2:$B$3001,A2004)) -> 479 | K2004: =IF(I2004=0,0,IF(H2004<=RFM_Method!$C$22,5,IF(H2004<=RFM_Method!$C$23,4,IF(H2004<=RFM_Method!$C$24,3,IF(H2004<=RFM_Method!$C$25,2,1))))) -> 1 | L2004: =IF(I2004=0,0,IF(I2004>=RFM_Method!$E$22,5,IF(I2004>=RFM_Method!$E$23,4,IF(I2004>=RFM_Method!$E$24,3,IF(I2004>=RFM_Method!$E$25,2,1))))) -> 1 | M2004: =IF(I2004=0,0,IF(J2004>=RFM_Method!$D$25,5,IF(J2004>=RFM_Method!$D$24,4,IF(J2004>=RFM_Method!$D$23,3,IF(J2004>=RFM_Method!$D$22,2,1))))) -> 2 | N2004: =K2004&L2004&M2004 -> 112 | O2004: =K2004+L2004+M2004 -> 4 | P2004: =IF(I2004=0,0,ROUND((L2004+M2004)/2,0)) -> 2 | Q2004: =IF(I2004=0,"Never Recharged",INDEX(RFM_Method!$C$32:$G$36,6-K2004,P2004)) -> Hibernating | R2004: =SUMIFS(Raw_DataUsage!$D$2:$D$5001,Raw_DataUsage!$B$2:$B$5001,A2004)/1024 -> 7.4375293 | S2004: =SUMIFS(Raw_Calls!$D$2:$D$5001,Raw_Calls!$B$2:$B$5001,A2004)/60 -> 49.883333 | T2004: =IF(COUNTIFS(Raw_Subscriptions!$B$2:$B$3001,A2004,Raw_Subscriptions!$F$2:$F$3001,"Active")>0,"Yes","No") -> Yes

Sheet Segment_Summary
A1: RFM Segment Summary
A2: All figures are live formulas over RFM_Calculation. Revenue = recharge ₹ in the 12-month window.
A4: Segment | B4: Description | C4: Priority | D4: Customers | E4: % Customers | F4: Avg Recency (days) | G4: Avg Frequency | H4: Avg Monetary (₹) | I4: Total Revenue (₹) | J4: % Revenue | K4: Avg Data Jan-26 (GB) | L4: Avg Call Mins | M4: % Active Subscription | N4: Avg RFM Total
A5: Champions | B5: Recharged very recently, recharge often and spend the most. | C5: Retain & Reward | D5: =COUNTIF(RFM_Calculation!$Q$5:$Q$2004,A5) -> 55 | E5: =IFERROR(D5/$D$17,0) -> 0.0275 | F5: =IFERROR(AVERAGEIFS(RFM_Calculation!$H$5:$H$2004,RFM_Calculation!$Q$5:$Q$2004,A5),"-") -> 34.236364 | G5: =IFERROR(AVERAGEIFS(RFM_Calculation!$I$5:$I$2004,RFM_Calculation!$Q$5:$Q$2004,A5),0) -> 4.7272727 | H5: =IFERROR(AVERAGEIFS(RFM_Calculation!$J$5:$J$2004,RFM_Calculation!$Q$5:$Q$2004,A5),0) -> 4508.6727 | I5: =SUMIFS(RFM_Calculation!$J$5:$J$2004,RFM_Calculation!$Q$5:$Q$2004,A5) -> 247977 | J5: =IFERROR(I5/$I$17,0) -> 0.11275551 | K5: =IFERROR(AVERAGEIFS(RFM_Calculation!$R$5:$R$2004,RFM_Calculation!$Q$5:$Q$2004,A5),0) -> 3.4251195 | L5: =IFERROR(AVERAGEIFS(RFM_Calculation!$S$5:$S$2004,RFM_Calculation!$Q$5:$Q$2004,A5),0) -> 76.568788 | M5: =IFERROR(COUNTIFS(RFM_Calculation!$Q$5:$Q$2004,A5,RFM_Calculation!$T$5:$T$2004,"Yes")/D5,0) -> 0.92727273 | N5: =IFERROR(AVERAGEIFS(RFM_Calculation!$O$5:$O$2004,RFM_Calculation!$Q$5:$Q$2004,A5),0) -> 13.890909
A6: Loyal Customers | B6: Spend well and recharge regularly; responsive to loyalty offers. | C6: Upsell | D6: =COUNTIF(RFM_Calculation!$Q$5:$Q$2004,A6) -> 311 | E6: =IFERROR(D6/$D$17,0) -> 0.1555 | F6: =IFERROR(AVERAGEIFS(RFM_Calculation!$H$5:$H$2004,RFM_Calculation!$Q$5:$Q$2004,A6),"-") -> 62.665595 | G6: =IFERROR(AVERAGEIFS(RFM_Calculation!$I$5:$I$2004,RFM_Calculation!$Q$5:$Q$2004,A6),0) -> 2.9935691 | H6: =IFERROR(AVERAGEIFS(RFM_Calculation!$J$5:$J$2004,RFM_Calculation!$Q$5:$Q$2004,A6),0) -> 2755.3762 | I6: =SUMIFS(RFM_Calculation!$J$5:$J$2004,RFM_Calculation!$Q$5:$Q$2004,A6) -> 856922 | J6: =IFERROR(I6/$I$17,0) -> 0.38964372 | K6: =IFERROR(AVERAGEIFS(RFM_Calculation!$R$5:$R$2004,RFM_Calculation!$Q$5:$Q$2004,A6),0) -> 3.0418912 | L6: =IFERROR(AVERAGEIFS(RFM_Calculation!$S$5:$S$2004,RFM_Calculation!$Q$5:$Q$2004,A6),0) -> 77.781565 | M6: =IFERROR(COUNTIFS(RFM_Calculation!$Q$5:$Q$2004,A6,RFM_Calculation!$T$5:$T$2004,"Yes")/D6,0) -> 0.74919614 | N6: =IFERROR(AVERAGEIFS(RFM_Calculation!$O$5:$O$2004,RFM_Calculation!$Q$5:$Q$2004,A6),0) -> 11.475884
A7: Potential Loyalist | B7: Recent customers with average frequency/spend; can become loyal. | C7: Nurture | D7: =COUNTIF(RFM_Calculation!$Q$5:$Q$2004,A7) -> 217 | E7: =IFERROR(D7/$D$17,0) -> 0.1085 | F7: =IFERROR(AVERAGEIFS(RFM_Calculation!$H$5:$H$2004,RFM_Calculation!$Q$5:$Q$2004,A7),"-") -> 47.668203 | G7: =IFERROR(AVERAGEIFS(RFM_Calculation!$I$5:$I$2004,RFM_Calculation!$Q$5:$Q$2004,A7),0) -> 1.8894009 | H7: =IFERROR(AVERAGEIFS(RFM_Calculation!$J$5:$J$2004,RFM_Calculation!$Q$5:$Q$2004,A7),0) -> 1140.7512 | I7: =SUMIFS(RFM_Calculation!$J$5:$J$2004,RFM_Calculation!$Q$5:$Q$2004,A7) -> 247543 | J7: =IFERROR(I7/$I$17,0) -> 0.11255817 | K7: =IFERROR(AVERAGEIFS(RFM_Calculation!$R$5:$R$2004,RFM_Calculation!$Q$5:$Q$2004,A7),0) -> 3.2167096 | L7: =IFERROR(AVERAGEIFS(RFM_Calculation!$S$5:$S$2004,RFM_Calculation!$Q$5:$Q$2004,A7),0) -> 73.961214 | M7: =IFERROR(COUNTIFS(RFM_Calculation!$Q$5:$Q$2004,A7,RFM_Calculation!$T$5:$T$2004,"Yes")/D7,0) -> 0.70967742 | N7: =IFERROR(AVERAGEIFS(RFM_Calculation!$O$5:$O$2004,RFM_Calculation!$Q$5:$Q$2004,A7),0) -> 9.3917051
A8: New Customers | B8: Recharged very recently but only once / low spend so far. | C8: Onboard | D8: =COUNTIF(RFM_Calculation!$Q$5:$Q$2004,A8) -> 34 | E8: =IFERROR(D8/$D$17,0) -> 0.017 | F8: =IFERROR(AVERAGEIFS(RFM_Calculation!$H$5:$H$2004,RFM_Calculation!$Q$5:$Q$2004,A8),"-") -> 20.970588 | G8: =IFERROR(AVERAGEIFS(RFM_Calculation!$I$5:$I$2004,RFM_Calculation!$Q$5:$Q$2004,A8),0) -> 1 | H8: =IFERROR(AVERAGEIFS(RFM_Calculation!$J$5:$J$2004,RFM_Calculation!$Q$5:$Q$2004,A8),0) -> 217.88235 | I8: =SUMIFS(RFM_Calculation!$J$5:$J$2004,RFM_Calculation!$Q$5:$Q$2004,A8) -> 7408 | J8: =IFERROR(I8/$I$17,0) -> 0.0033684287 | K8: =IFERROR(AVERAGEIFS(RFM_Calculation!$R$5:$R$2004,RFM_Calculation!$Q$5:$Q$2004,A8),0) -> 2.9780719 | L8: =IFERROR(AVERAGEIFS(RFM_Calculation!$S$5:$S$2004,RFM_Calculation!$Q$5:$Q$2004,A8),0) -> 86.693137 | M8: =IFERROR(COUNTIFS(RFM_Calculation!$Q$5:$Q$2004,A8,RFM_Calculation!$T$5:$T$2004,"Yes")/D8,0) -> 1 | N8: =IFERROR(AVERAGEIFS(RFM_Calculation!$O$5:$O$2004,RFM_Calculation!$Q$5:$Q$2004,A8),0) -> 7
A9: Promising | B9: Recent, low-to-mid spend; early interest worth building. | C9: Engage | D9: =COUNTIF(RFM_Calculation!$Q$5:$Q$2004,A9) -> 105 | E9: =IFERROR(D9/$D$17,0) -> 0.0525 | F9: =IFERROR(AVERAGEIFS(RFM_Calculation!$H$5:$H$2004,RFM_Calculation!$Q$5:$Q$2004,A9),"-") -> 36.933333 | G9: =IFERROR(AVERAGEIFS(RFM_Calculation!$I$5:$I$2004,RFM_Calculation!$Q$5:$Q$2004,A9),0) -> 1.2571429 | H9: =IFERROR(AVERAGEIFS(RFM_Calculation!$J$5:$J$2004,RFM_Calculation!$Q$5:$Q$2004,A9),0) -> 421.41905 | I9: =SUMIFS(RFM_Calculation!$J$5:$J$2004,RFM_Calculation!$Q$5:$Q$2004,A9) -> 44249 | J9: =IFERROR(I9/$I$17,0) -> 0.020120087 | K9: =IFERROR(AVERAGEIFS(RFM_Calculation!$R$5:$R$2004,RFM_Calculation!$Q$5:$Q$2004,A9),0) -> 2.8150835 | L9: =IFERROR(AVERAGEIFS(RFM_Calculation!$S$5:$S$2004,RFM_Calculation!$Q$5:$Q$2004,A9),0) -> 65.900794 | M9: =IFERROR(COUNTIFS(RFM_Calculation!$Q$5:$Q$2004,A9,RFM_Calculation!$T$5:$T$2004,"Yes")/D9,0) -> 0.8 | N9: =IFERROR(AVERAGEIFS(RFM_Calculation!$O$5:$O$2004,RFM_Calculation!$Q$5:$Q$2004,A9),0) -> 7.4857143
A10: Need Attention | B10: Average recency, frequency and spend; starting to slip. | C10: Re-engage | D10: =COUNTIF(RFM_Calculation!$Q$5:$Q$2004,A10) -> 153 | E10: =IFERROR(D10/$D$17,0) -> 0.0765 | F10: =IFERROR(AVERAGEIFS(RFM_Calculation!$H$5:$H$2004,RFM_Calculation!$Q$5:$Q$2004,A10),"-") -> 112.41176 | G10: =IFERROR(AVERAGEIFS(RFM_Calculation!$I$5:$I$2004,RFM_Calculation!$Q$5:$Q$2004,A10),0) -> 1.7908497 | H10: =IFERROR(AVERAGEIFS(RFM_Calculation!$J$5:$J$2004,RFM_Calculation!$Q$5:$Q$2004,A10),0) -> 939.78431 | I10: =SUMIFS(RFM_Calculation!$J$5:$J$2004,RFM_Calculation!$Q$5:$Q$2004,A10) -> 143787 | J10: =IFERROR(I10/$I$17,0) -> 0.065380165 | K10: =IFERROR(AVERAGEIFS(RFM_Calculation!$R$5:$R$2004,RFM_Calculation!$Q$5:$Q$2004,A10),0) -> 3.0826419 | L10: =IFERROR(AVERAGEIFS(RFM_Calculation!$S$5:$S$2004,RFM_Calculation!$Q$5:$Q$2004,A10),0) -> 73.31841 | M10: =IFERROR(COUNTIFS(RFM_Calculation!$Q$5:$Q$2004,A10,RFM_Calculation!$T$5:$T$2004,"Yes")/D10,0) -> 0.31372549 | N10: =IFERROR(AVERAGEIFS(RFM_Calculation!$O$5:$O$2004,RFM_Calculation!$Q$5:$Q$2004,A10),0) -> 7.6732026
A11: About to Sleep | B11: Below-average recency and value; will lapse without a nudge. | C11: Remind | D11: =COUNTIF(RFM_Calculation!$Q$5:$Q$2004,A11) -> 157 | E11: =IFERROR(D11/$D$17,0) -> 0.0785 | F11: =IFERROR(AVERAGEIFS(RFM_Calculation!$H$5:$H$2004,RFM_Calculation!$Q$5:$Q$2004,A11),"-") -> 166.34395 | G11: =IFERROR(AVERAGEIFS(RFM_Calculation!$I$5:$I$2004,RFM_Calculation!$Q$5:$Q$2004,A11),0) -> 1.1910828 | H11: =IFERROR(AVERAGEIFS(RFM_Calculation!$J$5:$J$2004,RFM_Calculation!$Q$5:$Q$2004,A11),0) -> 482.6879 | I11: =SUMIFS(RFM_Calculation!$J$5:$J$2004,RFM_Calculation!$Q$5:$Q$2004,A11) -> 75782 | J11: =IFERROR(I11/$I$17,0) -> 0.034458189 | K11: =IFERROR(AVERAGEIFS(RFM_Calculation!$R$5:$R$2004,RFM_Calculation!$Q$5:$Q$2004,A11),0) -> 3.044419 | L11: =IFERROR(AVERAGEIFS(RFM_Calculation!$S$5:$S$2004,RFM_Calculation!$Q$5:$Q$2004,A11),0) -> 73.29087 | M11: =IFERROR(COUNTIFS(RFM_Calculation!$Q$5:$Q$2004,A11,RFM_Calculation!$T$5:$T$2004,"Yes")/D11,0) -> 0.25477707 | N11: =IFERROR(AVERAGEIFS(RFM_Calculation!$O$5:$O$2004,RFM_Calculation!$Q$5:$Q$2004,A11),0) -> 5.3757962
A12: At Risk | B12: Used to recharge/spend well but have not come back for a while. | C12: Win-back | D12: =COUNTIF(RFM_Calculation!$Q$5:$Q$2004,A12) -> 204 | E12: =IFERROR(D12/$D$17,0) -> 0.102 | F12: =IFERROR(AVERAGEIFS(RFM_Calculation!$H$5:$H$2004,RFM_Calculation!$Q$5:$Q$2004,A12),"-") -> 213.0098 | G12: =IFERROR(AVERAGEIFS(RFM_Calculation!$I$5:$I$2004,RFM_Calculation!$Q$5:$Q$2004,A12),0) -> 2.0637255 | H12: =IFERROR(AVERAGEIFS(RFM_Calculation!$J$5:$J$2004,RFM_Calculation!$Q$5:$Q$2004,A12),0) -> 1876.5539 | I12: =SUMIFS(RFM_Calculation!$J$5:$J$2004,RFM_Calculation!$Q$5:$Q$2004,A12) -> 382817 | J12: =IFERROR(I12/$I$17,0) -> 0.17406746 | K12: =IFERROR(AVERAGEIFS(RFM_Calculation!$R$5:$R$2004,RFM_Calculation!$Q$5:$Q$2004,A12),0) -> 2.9225227 | L12: =IFERROR(AVERAGEIFS(RFM_Calculation!$S$5:$S$2004,RFM_Calculation!$Q$5:$Q$2004,A12),0) -> 76.670915 | M12: =IFERROR(COUNTIFS(RFM_Calculation!$Q$5:$Q$2004,A12,RFM_Calculation!$T$5:$T$2004,"Yes")/D12,0) -> 0.34803922 | N12: =IFERROR(AVERAGEIFS(RFM_Calculation!$O$5:$O$2004,RFM_Calculation!$Q$5:$Q$2004,A12),0) -> 7.7156863
A13: Can't Lose Them | B13: High value historically, now long inactive - biggest revenue risk. | C13: Urgent Retention | D13: =COUNTIF(RFM_Calculation!$Q$5:$Q$2004,A13) -> 20 | E13: =IFERROR(D13/$D$17,0) -> 0.01 | F13: =IFERROR(AVERAGEIFS(RFM_Calculation!$H$5:$H$2004,RFM_Calculation!$Q$5:$Q$2004,A13),"-") -> 245.05 | G13: =IFERROR(AVERAGEIFS(RFM_Calculation!$I$5:$I$2004,RFM_Calculation!$Q$5:$Q$2004,A13),0) -> 2.8 | H13: =IFERROR(AVERAGEIFS(RFM_Calculation!$J$5:$J$2004,RFM_Calculation!$Q$5:$Q$2004,A13),0) -> 3932.8 | I13: =SUMIFS(RFM_Calculation!$J$5:$J$2004,RFM_Calculation!$Q$5:$Q$2004,A13) -> 78656 | J13: =IFERROR(I13/$I$17,0) -> 0.035765001 | K13: =IFERROR(AVERAGEIFS(RFM_Calculation!$R$5:$R$2004,RFM_Calculation!$Q$5:$Q$2004,A13),0) -> 2.7629321 | L13: =IFERROR(AVERAGEIFS(RFM_Calculation!$S$5:$S$2004,RFM_Calculation!$Q$5:$Q$2004,A13),0) -> 91.006667 | M13: =IFERROR(COUNTIFS(RFM_Calculation!$Q$5:$Q$2004,A13,RFM_Calculation!$T$5:$T$2004,"Yes")/D13,0) -> 0.65 | N13: =IFERROR(AVERAGEIFS(RFM_Calculation!$O$5:$O$2004,RFM_Calculation!$Q$5:$Q$2004,A13),0) -> 9
A14: Hibernating | B14: Low value, long since last recharge. | C14: Low-cost Reactivate | D14: =COUNTIF(RFM_Calculation!$Q$5:$Q$2004,A14) -> 185 | E14: =IFERROR(D14/$D$17,0) -> 0.0925 | F14: =IFERROR(AVERAGEIFS(RFM_Calculation!$H$5:$H$2004,RFM_Calculation!$Q$5:$Q$2004,A14),"-") -> 267.37297 | G14: =IFERROR(AVERAGEIFS(RFM_Calculation!$I$5:$I$2004,RFM_Calculation!$Q$5:$Q$2004,A14),0) -> 1.0972973 | H14: =IFERROR(AVERAGEIFS(RFM_Calculation!$J$5:$J$2004,RFM_Calculation!$Q$5:$Q$2004,A14),0) -> 506.57838 | I14: =SUMIFS(RFM_Calculation!$J$5:$J$2004,RFM_Calculation!$Q$5:$Q$2004,A14) -> 93717 | J14: =IFERROR(I14/$I$17,0) -> 0.04261326 | K14: =IFERROR(AVERAGEIFS(RFM_Calculation!$R$5:$R$2004,RFM_Calculation!$Q$5:$Q$2004,A14),0) -> 3.2649251 | L14: =IFERROR(AVERAGEIFS(RFM_Calculation!$S$5:$S$2004,RFM_Calculation!$Q$5:$Q$2004,A14),0) -> 63.164324 | M14: =IFERROR(COUNTIFS(RFM_Calculation!$Q$5:$Q$2004,A14,RFM_Calculation!$T$5:$T$2004,"Yes")/D14,0) -> 0.18918919 | N14: =IFERROR(AVERAGEIFS(RFM_Calculation!$O$5:$O$2004,RFM_Calculation!$Q$5:$Q$2004,A14),0) -> 4.3297297
A15: Lost | B15: Lowest recency, frequency and spend. | C15: Last-chance / Suppress | D15: =COUNTIF(RFM_Calculation!$Q$5:$Q$2004,A15) -> 92 | E15: =IFERROR(D15/$D$17,0) -> 0.046 | F15: =IFERROR(AVERAGEIFS(RFM_Calculation!$H$5:$H$2004,RFM_Calculation!$Q$5:$Q$2004,A15),"-") -> 298.8587 | G15: =IFERROR(AVERAGEIFS(RFM_Calculation!$I$5:$I$2004,RFM_Calculation!$Q$5:$Q$2004,A15),0) -> 1 | H15: =IFERROR(AVERAGEIFS(RFM_Calculation!$J$5:$J$2004,RFM_Calculation!$Q$5:$Q$2004,A15),0) -> 221.59783 | I15: =SUMIFS(RFM_Calculation!$J$5:$J$2004,RFM_Calculation!$Q$5:$Q$2004,A15) -> 20387 | J15: =IFERROR(I15/$I$17,0) -> 0.0092699995 | K15: =IFERROR(AVERAGEIFS(RFM_Calculation!$R$5:$R$2004,RFM_Calculation!$Q$5:$Q$2004,A15),0) -> 2.6070121 | L15: =IFERROR(AVERAGEIFS(RFM_Calculation!$S$5:$S$2004,RFM_Calculation!$Q$5:$Q$2004,A15),0) -> 83.375 | M15: =IFERROR(COUNTIFS(RFM_Calculation!$Q$5:$Q$2004,A15,RFM_Calculation!$T$5:$T$2004,"Yes")/D15,0) -> 0.29347826 | N15: =IFERROR(AVERAGEIFS(RFM_Calculation!$O$5:$O$2004,RFM_Calculation!$Q$5:$Q$2004,A15),0) -> 3
A16: Never Recharged | B16: Registered customers with no recharge in the 12-month window. | C16: Activate | D16: =COUNTIF(RFM_Calculation!$Q$5:$Q$2004,A16) -> 467 | E16: =IFERROR(D16/$D$17,0) -> 0.2335 | F16: =IFERROR(AVERAGEIFS(RFM_Calculation!$H$5:$H$2004,RFM_Calculation!$Q$5:$Q$2004,A16),"-") -> - | G16: =IFERROR(AVERAGEIFS(RFM_Calculation!$I$5:$I$2004,RFM_Calculation!$Q$5:$Q$2004,A16),0) -> 0 | H16: =IFERROR(AVERAGEIFS(RFM_Calculation!$J$5:$J$2004,RFM_Calculation!$Q$5:$Q$2004,A16),0) -> 0 | I16: =SUMIFS(RFM_Calculation!$J$5:$J$2004,RFM_Calculation!$Q$5:$Q$2004,A16) -> 0 | J16: =IFERROR(I16/$I$17,0) -> 0 | K16: =IFERROR(AVERAGEIFS(RFM_Calculation!$R$5:$R$2004,RFM_Calculation!$Q$5:$Q$2004,A16),0) -> 3.238174 | L16: =IFERROR(AVERAGEIFS(RFM_Calculation!$S$5:$S$2004,RFM_Calculation!$Q$5:$Q$2004,A16),0) -> 76.269201 | M16: =IFERROR(COUNTIFS(RFM_Calculation!$Q$5:$Q$2004,A16,RFM_Calculation!$T$5:$T$2004,"Yes")/D16,0) -> 0 | N16: =IFERROR(AVERAGEIFS(RFM_Calculation!$O$5:$O$2004,RFM_Calculation!$Q$5:$Q$2004,A16),0) -> 0
A17: Total | D17: =SUM(D5:D16) -> 2000 | E17: =SUM(E5:E16) -> 1 | F17: =AVERAGE(RFM_Calculation!$H$5:$H$2004) -> 133.68297 | G17: =AVERAGEIF(RFM_Calculation!$I$5:$I$2004,">0") -> 1.9569472 | H17: =AVERAGE(RFM_Calculation!$J$5:$J$2004) -> 1434.6021 | I17: =SUM(I5:I16) -> 2199245 | J17: =SUM(J5:J16) -> 1 | K17: =AVERAGE(RFM_Calculation!$R$5:$R$2004) -> 3.0932144 | L17: =AVERAGE(RFM_Calculation!$S$5:$S$2004) -> 74.738542 | M17: =COUNTIF(RFM_Calculation!$T$5:$T$2004,"Yes")/D17 -> 0.395 | N17: =AVERAGEIF(RFM_Calculation!$O$5:$O$2004,">0") -> 7.9869537
I18: =IF(ROUND(I17-RFM_Method!$C$8,0)=0,"✓ ties to raw revenue","CHECK: does not tie to raw") -> ✓ ties to raw revenue
A20: Score distribution (recharging customers)
A21: Score | B21: R Score count | C21: F Score count | D21: M Score count
A22: 5 | B22: =COUNTIF(RFM_Calculation!$K$5:$K$2004,$A22) -> 310 | C22: =COUNTIF(RFM_Calculation!$L$5:$L$2004,$A22) -> 33 | D22: =COUNTIF(RFM_Calculation!$M$5:$M$2004,$A22) -> 313
A23: 4 | B23: =COUNTIF(RFM_Calculation!$K$5:$K$2004,$A23) -> 304 | C23: =COUNTIF(RFM_Calculation!$L$5:$L$2004,$A23) -> 97 | D23: =COUNTIF(RFM_Calculation!$M$5:$M$2004,$A23) -> 309
A24: 3 | B24: =COUNTIF(RFM_Calculation!$K$5:$K$2004,$A24) -> 308 | C24: =COUNTIF(RFM_Calculation!$L$5:$L$2004,$A24) -> 264 | D24: =COUNTIF(RFM_Calculation!$M$5:$M$2004,$A24) -> 321
A25: 2 | B25: =COUNTIF(RFM_Calculation!$K$5:$K$2004,$A25) -> 308 | C25: =COUNTIF(RFM_Calculation!$L$5:$L$2004,$A25) -> 503 | D25: =COUNTIF(RFM_Calculation!$M$5:$M$2004,$A25) -> 294
A26: 1 | B26: =COUNTIF(RFM_Calculation!$K$5:$K$2004,$A26) -> 303 | C26: =COUNTIF(RFM_Calculation!$L$5:$L$2004,$A26) -> 636 | D26: =COUNTIF(RFM_Calculation!$M$5:$M$2004,$A26) -> 296
A29: Customers by Telecom Circle x Segment
A30: Circle | B30: Champions | C30: Loyal Customers | D30: Potential Loyalist | E30: New Customers | F30: Promising | G30: Need Attention | H30: About to Sleep | I30: At Risk | J30: Can't Lose Them | K30: Hibernating | L30: Lost | M30: Never Recharged | N30: Total
A31: Andhra Pradesh | B31: =COUNTIFS(RFM_Calculation!$D$5:$D$2004,$A31,RFM_Calculation!$Q$5:$Q$2004,B$30) -> 3 | C31: =COUNTIFS(RFM_Calculation!$D$5:$D$2004,$A31,RFM_Calculation!$Q$5:$Q$2004,C$30) -> 25 | D31: =COUNTIFS(RFM_Calculation!$D$5:$D$2004,$A31,RFM_Calculation!$Q$5:$Q$2004,D$30) -> 13 | E31: =COUNTIFS(RFM_Calculation!$D$5:$D$2004,$A31,RFM_Calculation!$Q$5:$Q$2004,E$30) -> 3 | F31: =COUNTIFS(RFM_Calculation!$D$5:$D$2004,$A31,RFM_Calculation!$Q$5:$Q$2004,F$30) -> 5 | G31: =COUNTIFS(RFM_Calculation!$D$5:$D$2004,$A31,RFM_Calculation!$Q$5:$Q$2004,G$30) -> 9 | H31: =COUNTIFS(RFM_Calculation!$D$5:$D$2004,$A31,RFM_Calculation!$Q$5:$Q$2004,H$30) -> 11 | I31: =COUNTIFS(RFM_Calculation!$D$5:$D$2004,$A31,RFM_Calculation!$Q$5:$Q$2004,I$30) -> 14 | ... M31: =COUNTIFS(RFM_Calculation!$D$5:$D$2004,$A31,RFM_Calculation!$Q$5:$Q$2004,M$30) -> 26 | N31: =SUM(B31:M31) -> 131
A32: Delhi NCR | B32: =COUNTIFS(RFM_Calculation!$D$5:$D$2004,$A32,RFM_Calculation!$Q$5:$Q$2004,B$30) -> 6 | C32: =COUNTIFS(RFM_Calculation!$D$5:$D$2004,$A32,RFM_Calculation!$Q$5:$Q$2004,C$30) -> 26 | D32: =COUNTIFS(RFM_Calculation!$D$5:$D$2004,$A32,RFM_Calculation!$Q$5:$Q$2004,D$30) -> 19 | E32: =COUNTIFS(RFM_Calculation!$D$5:$D$2004,$A32,RFM_Calculation!$Q$5:$Q$2004,E$30) -> 6 | F32: =COUNTIFS(RFM_Calculation!$D$5:$D$2004,$A32,RFM_Calculation!$Q$5:$Q$2004,F$30) -> 7 | G32: =COUNTIFS(RFM_Calculation!$D$5:$D$2004,$A32,RFM_Calculation!$Q$5:$Q$2004,G$30) -> 13 | H32: =COUNTIFS(RFM_Calculation!$D$5:$D$2004,$A32,RFM_Calculation!$Q$5:$Q$2004,H$30) -> 14 | I32: =COUNTIFS(RFM_Calculation!$D$5:$D$2004,$A32,RFM_Calculation!$Q$5:$Q$2004,I$30) -> 12 | ... M32: =COUNTIFS(RFM_Calculation!$D$5:$D$2004,$A32,RFM_Calculation!$Q$5:$Q$2004,M$30) -> 35 | N32: =SUM(B32:M32) -> 159
A33: Gujarat | B33: =COUNTIFS(RFM_Calculation!$D$5:$D$2004,$A33,RFM_Calculation!$Q$5:$Q$2004,B$30) -> 4 | C33: =COUNTIFS(RFM_Calculation!$D$5:$D$2004,$A33,RFM_Calculation!$Q$5:$Q$2004,C$30) -> 29 | D33: =COUNTIFS(RFM_Calculation!$D$5:$D$2004,$A33,RFM_Calculation!$Q$5:$Q$2004,D$30) -> 22 | E33: =COUNTIFS(RFM_Calculation!$D$5:$D$2004,$A33,RFM_Calculation!$Q$5:$Q$2004,E$30) -> 3 | F33: =COUNTIFS(RFM_Calculation!$D$5:$D$2004,$A33,RFM_Calculation!$Q$5:$Q$2004,F$30) -> 13 | G33: =COUNTIFS(RFM_Calculation!$D$5:$D$2004,$A33,RFM_Calculation!$Q$5:$Q$2004,G$30) -> 8 | H33: =COUNTIFS(RFM_Calculation!$D$5:$D$2004,$A33,RFM_Calculation!$Q$5:$Q$2004,H$30) -> 10 | I33: =COUNTIFS(RFM_Calculation!$D$5:$D$2004,$A33,RFM_Calculation!$Q$5:$Q$2004,I$30) -> 24 | ... M33: =COUNTIFS(RFM_Calculation!$D$5:$D$2004,$A33,RFM_Calculation!$Q$5:$Q$2004,M$30) -> 41 | N33: =SUM(B33:M33) -> 180
A34: Karnataka | B34: =COUNTIFS(RFM_Calculation!$D$5:$D$2004,$A34,RFM_Calculation!$Q$5:$Q$2004,B$30) -> 5 | C34: =COUNTIFS(RFM_Calculation!$D$5:$D$2004,$A34,RFM_Calculation!$Q$5:$Q$2004,C$30) -> 26 | D34: =COUNTIFS(RFM_Calculation!$D$5:$D$2004,$A34,RFM_Calculation!$Q$5:$Q$2004,D$30) -> 13 | E34: =COUNTIFS(RFM_Calculation!$D$5:$D$2004,$A34,RFM_Calculation!$Q$5:$Q$2004,E$30) -> 0 | F34: =COUNTIFS(RFM_Calculation!$D$5:$D$2004,$A34,RFM_Calculation!$Q$5:$Q$2004,F$30) -> 6 | G34: =COUNTIFS(RFM_Calculation!$D$5:$D$2004,$A34,RFM_Calculation!$Q$5:$Q$2004,G$30) -> 22 | H34: =COUNTIFS(RFM_Calculation!$D$5:$D$2004,$A34,RFM_Calculation!$Q$5:$Q$2004,H$30) -> 12 | I34: =COUNTIFS(RFM_Calculation!$D$5:$D$2004,$A34,RFM_Calculation!$Q$5:$Q$2004,I$30) -> 24 | ... M34: =COUNTIFS(RFM_Calculation!$D$5:$D$2004,$A34,RFM_Calculation!$Q$5:$Q$2004,M$30) -> 35 | N34: =SUM(B34:M34) -> 166
A35: Maharashtra | B35: =COUNTIFS(RFM_Calculation!$D$5:$D$2004,$A35,RFM_Calculation!$Q$5:$Q$2004,B$30) -> 3 | C35: =COUNTIFS(RFM_Calculation!$D$5:$D$2004,$A35,RFM_Calculation!$Q$5:$Q$2004,C$30) -> 30 | D35: =COUNTIFS(RFM_Calculation!$D$5:$D$2004,$A35,RFM_Calculation!$Q$5:$Q$2004,D$30) -> 14 | E35: =COUNTIFS(RFM_Calculation!$D$5:$D$2004,$A35,RFM_Calculation!$Q$5:$Q$2004,E$30) -> 2 | F35: =COUNTIFS(RFM_Calculation!$D$5:$D$2004,$A35,RFM_Calculation!$Q$5:$Q$2004,F$30) -> 6 | G35: =COUNTIFS(RFM_Calculation!$D$5:$D$2004,$A35,RFM_Calculation!$Q$5:$Q$2004,G$30) -> 12 | H35: =COUNTIFS(RFM_Calculation!$D$5:$D$2004,$A35,RFM_Calculation!$Q$5:$Q$2004,H$30) -> 9 | I35: =COUNTIFS(RFM_Calculation!$D$5:$D$2004,$A35,RFM_Calculation!$Q$5:$Q$2004,I$30) -> 13 | ... M35: =COUNTIFS(RFM_Calculation!$D$5:$D$2004,$A35,RFM_Calculation!$Q$5:$Q$2004,M$30) -> 46 | N35: =SUM(B35:M35) -> 171
A36: Mumbai | B36: =COUNTIFS(RFM_Calculation!$D$5:$D$2004,$A36,RFM_Calculation!$Q$5:$Q$2004,B$30) -> 2 | C36: =COUNTIFS(RFM_Calculation!$D$5:$D$2004,$A36,RFM_Calculation!$Q$5:$Q$2004,C$30) -> 23 | D36: =COUNTIFS(RFM_Calculation!$D$5:$D$2004,$A36,RFM_Calculation!$Q$5:$Q$2004,D$30) -> 23 | E36: =COUNTIFS(RFM_Calculation!$D$5:$D$2004,$A36,RFM_Calculation!$Q$5:$Q$2004,E$30) -> 2 | F36: =COUNTIFS(RFM_Calculation!$D$5:$D$2004,$A36,RFM_Calculation!$Q$5:$Q$2004,F$30) -> 11 | G36: =COUNTIFS(RFM_Calculation!$D$5:$D$2004,$A36,RFM_Calculation!$Q$5:$Q$2004,G$30) -> 10 | H36: =COUNTIFS(RFM_Calculation!$D$5:$D$2004,$A36,RFM_Calculation!$Q$5:$Q$2004,H$30) -> 10 | I36: =COUNTIFS(RFM_Calculation!$D$5:$D$2004,$A36,RFM_Calculation!$Q$5:$Q$2004,I$30) -> 13 | ... M36: =COUNTIFS(RFM_Calculation!$D$5:$D$2004,$A36,RFM_Calculation!$Q$5:$Q$2004,M$30) -> 40 | N36: =SUM(B36:M36) -> 158
A37: Punjab | B37: =COUNTIFS(RFM_Calculation!$D$5:$D$2004,$A37,RFM_Calculation!$Q$5:$Q$2004,B$30) -> 4 | C37: =COUNTIFS(RFM_Calculation!$D$5:$D$2004,$A37,RFM_Calculation!$Q$5:$Q$2004,C$30) -> 26 | D37: =COUNTIFS(RFM_Calculation!$D$5:$D$2004,$A37,RFM_Calculation!$Q$5:$Q$2004,D$30) -> 25 | E37: =COUNTIFS(RFM_Calculation!$D$5:$D$2004,$A37,RFM_Calculation!$Q$5:$Q$2004,E$30) -> 3 | F37: =COUNTIFS(RFM_Calculation!$D$5:$D$2004,$A37,RFM_Calculation!$Q$5:$Q$2004,F$30) -> 19 | G37: =COUNTIFS(RFM_Calculation!$D$5:$D$2004,$A37,RFM_Calculation!$Q$5:$Q$2004,G$30) -> 14 | H37: =COUNTIFS(RFM_Calculation!$D$5:$D$2004,$A37,RFM_Calculation!$Q$5:$Q$2004,H$30) -> 23 | I37: =COUNTIFS(RFM_Calculation!$D$5:$D$2004,$A37,RFM_Calculation!$Q$5:$Q$2004,I$30) -> 16 | ... M37: =COUNTIFS(RFM_Calculation!$D$5:$D$2004,$A37,RFM_Calculation!$Q$5:$Q$2004,M$30) -> 37 | N37: =SUM(B37:M37) -> 192
A38: Tamil Nadu | B38: =COUNTIFS(RFM_Calculation!$D$5:$D$2004,$A38,RFM_Calculation!$Q$5:$Q$2004,B$30) -> 4 | C38: =COUNTIFS(RFM_Calculation!$D$5:$D$2004,$A38,RFM_Calculation!$Q$5:$Q$2004,C$30) -> 24 | D38: =COUNTIFS(RFM_Calculation!$D$5:$D$2004,$A38,RFM_Calculation!$Q$5:$Q$2004,D$30) -> 23 | E38: =COUNTIFS(RFM_Calculation!$D$5:$D$2004,$A38,RFM_Calculation!$Q$5:$Q$2004,E$30) -> 5 | F38: =COUNTIFS(RFM_Calculation!$D$5:$D$2004,$A38,RFM_Calculation!$Q$5:$Q$2004,F$30) -> 7 | G38: =COUNTIFS(RFM_Calculation!$D$5:$D$2004,$A38,RFM_Calculation!$Q$5:$Q$2004,G$30) -> 19 | H38: =COUNTIFS(RFM_Calculation!$D$5:$D$2004,$A38,RFM_Calculation!$Q$5:$Q$2004,H$30) -> 20 | I38: =COUNTIFS(RFM_Calculation!$D$5:$D$2004,$A38,RFM_Calculation!$Q$5:$Q$2004,I$30) -> 21 | ... M38: =COUNTIFS(RFM_Calculation!$D$5:$D$2004,$A38,RFM_Calculation!$Q$5:$Q$2004,M$30) -> 42 | N38: =SUM(B38:M38) -> 192
A39: Telangana | B39: =COUNTIFS(RFM_Calculation!$D$5:$D$2004,$A39,RFM_Calculation!$Q$5:$Q$2004,B$30) -> 8 | C39: =COUNTIFS(RFM_Calculation!$D$5:$D$2004,$A39,RFM_Calculation!$Q$5:$Q$2004,C$30) -> 22 | D39: =COUNTIFS(RFM_Calculation!$D$5:$D$2004,$A39,RFM_Calculation!$Q$5:$Q$2004,D$30) -> 17 | E39: =COUNTIFS(RFM_Calculation!$D$5:$D$2004,$A39,RFM_Calculation!$Q$5:$Q$2004,E$30) -> 2 | F39: =COUNTIFS(RFM_Calculation!$D$5:$D$2004,$A39,RFM_Calculation!$Q$5:$Q$2004,F$30) -> 10 | G39: =COUNTIFS(RFM_Calculation!$D$5:$D$2004,$A39,RFM_Calculation!$Q$5:$Q$2004,G$30) -> 11 | H39: =COUNTIFS(RFM_Calculation!$D$5:$D$2004,$A39,RFM_Calculation!$Q$5:$Q$2004,H$30) -> 9 | I39: =COUNTIFS(RFM_Calculation!$D$5:$D$2004,$A39,RFM_Calculation!$Q$5:$Q$2004,I$30) -> 22 | ... M39: =COUNTIFS(RFM_Calculation!$D$5:$D$2004,$A39,RFM_Calculation!$Q$5:$Q$2004,M$30) -> 34 | N39: =SUM(B39:M39) -> 165
A40: UP East | B40: =COUNTIFS(RFM_Calculation!$D$5:$D$2004,$A40,RFM_Calculation!$Q$5:$Q$2004,B$30) -> 5 | C40: =COUNTIFS(RFM_Calculation!$D$5:$D$2004,$A40,RFM_Calculation!$Q$5:$Q$2004,C$30) -> 34 | D40: =COUNTIFS(RFM_Calculation!$D$5:$D$2004,$A40,RFM_Calculation!$Q$5:$Q$2004,D$30) -> 24 | E40: =COUNTIFS(RFM_Calculation!$D$5:$D$2004,$A40,RFM_Calculation!$Q$5:$Q$2004,E$30) -> 1 | F40: =COUNTIFS(RFM_Calculation!$D$5:$D$2004,$A40,RFM_Calculation!$Q$5:$Q$2004,F$30) -> 9 | G40: =COUNTIFS(RFM_Calculation!$D$5:$D$2004,$A40,RFM_Calculation!$Q$5:$Q$2004,G$30) -> 13 | H40: =COUNTIFS(RFM_Calculation!$D$5:$D$2004,$A40,RFM_Calculation!$Q$5:$Q$2004,H$30) -> 18 | I40: =COUNTIFS(RFM_Calculation!$D$5:$D$2004,$A40,RFM_Calculation!$Q$5:$Q$2004,I$30) -> 14 | ... M40: =COUNTIFS(RFM_Calculation!$D$5:$D$2004,$A40,RFM_Calculation!$Q$5:$Q$2004,M$30) -> 46 | N40: =SUM(B40:M40) -> 189
A41: UP West | B41: =COUNTIFS(RFM_Calculation!$D$5:$D$2004,$A41,RFM_Calculation!$Q$5:$Q$2004,B$30) -> 9 | C41: =COUNTIFS(RFM_Calculation!$D$5:$D$2004,$A41,RFM_Calculation!$Q$5:$Q$2004,C$30) -> 23 | D41: =COUNTIFS(RFM_Calculation!$D$5:$D$2004,$A41,RFM_Calculation!$Q$5:$Q$2004,D$30) -> 7 | E41: =COUNTIFS(RFM_Calculation!$D$5:$D$2004,$A41,RFM_Calculation!$Q$5:$Q$2004,E$30) -> 2 | F41: =COUNTIFS(RFM_Calculation!$D$5:$D$2004,$A41,RFM_Calculation!$Q$5:$Q$2004,F$30) -> 7 | G41: =COUNTIFS(RFM_Calculation!$D$5:$D$2004,$A41,RFM_Calculation!$Q$5:$Q$2004,G$30) -> 11 | H41: =COUNTIFS(RFM_Calculation!$D$5:$D$2004,$A41,RFM_Calculation!$Q$5:$Q$2004,H$30) -> 10 | I41: =COUNTIFS(RFM_Calculation!$D$5:$D$2004,$A41,RFM_Calculation!$Q$5:$Q$2004,I$30) -> 12 | ... M41: =COUNTIFS(RFM_Calculation!$D$5:$D$2004,$A41,RFM_Calculation!$Q$5:$Q$2004,M$30) -> 44 | N41: =SUM(B41:M41) -> 141
A42: West Bengal | B42: =COUNTIFS(RFM_Calculation!$D$5:$D$2004,$A42,RFM_Calculation!$Q$5:$Q$2004,B$30) -> 2 | C42: =COUNTIFS(RFM_Calculation!$D$5:$D$2004,$A42,RFM_Calculation!$Q$5:$Q$2004,C$30) -> 23 | D42: =COUNTIFS(RFM_Calculation!$D$5:$D$2004,$A42,RFM_Calculation!$Q$5:$Q$2004,D$30) -> 17 | E42: =COUNTIFS(RFM_Calculation!$D$5:$D$2004,$A42,RFM_Calculation!$Q$5:$Q$2004,E$30) -> 5 | F42: =COUNTIFS(RFM_Calculation!$D$5:$D$2004,$A42,RFM_Calculation!$Q$5:$Q$2004,F$30) -> 5 | G42: =COUNTIFS(RFM_Calculation!$D$5:$D$2004,$A42,RFM_Calculation!$Q$5:$Q$2004,G$30) -> 11 | H42: =COUNTIFS(RFM_Calculation!$D$5:$D$2004,$A42,RFM_Calculation!$Q$5:$Q$2004,H$30) -> 11 | I42: =COUNTIFS(RFM_Calculation!$D$5:$D$2004,$A42,RFM_Calculation!$Q$5:$Q$2004,I$30) -> 19 | ... M42: =COUNTIFS(RFM_Calculation!$D$5:$D$2004,$A42,RFM_Calculation!$Q$5:$Q$2004,M$30) -> 41 | N42: =SUM(B42:M42) -> 156

Sheet Marketing_Strategy
A1: Digital Marketing Strategy by RFM Segment
A2: Offers use the existing plan catalogue (Raw_Plans). Segment size & revenue pull live from Segment_Summary. Budget share (blue) is an editable input.
A4: Segment | B4: Customers | C4: Revenue Share | D4: Objective | E4: Core Offer / Hook | F4: Plan(s) to Push | G4: Primary Channels | H4: Message Angle | I4: Timing & Frequency | J4: CTA | K4: KPIs | L4: Budget Share
A5: Champions | B5: =Segment_Summary!D5 -> 55 | C5: =Segment_Summary!J5 -> 0.11275551 | D5: Retain, reward & turn into advocates | E5: VIP 'Elite Club': 10% cashback on Annual Plan renewal + 3 months free OTT; refer-a-friend ₹100 each side | F5: P003 Annual ₹2999, P006 Family ₹999 | G5: App push, WhatsApp Business, Email, RCS | H5: "You're our top 1% - here's what you've unlocked" (exclusivity, gratitude) | I5: Monthly VIP drop; 7 days before validity ends | J5: Claim VIP reward | K5: Renewal rate, referrals, ARPU | L5: 0.1
A6: Loyal Customers | B6: =Segment_Summary!D6 -> 311 | C6: =Segment_Summary!J6 -> 0.38964372 | D6: Upsell to higher ARPU / postpaid | E6: Switch to Infinity 499 Postpaid - 1st month FREE + 75GB; ₹50 off every recharge on Auto-Pay | F6: P007 Infinity ₹499, P002 ₹479 | G6: App push, WhatsApp, Instagram/Facebook custom audience | H6: "More data, no recharge reminders, same loyalty" | I6: Bi-weekly; trigger on 3rd recharge | J6: Upgrade now | K6: Upgrade %, Auto-Pay enrolments | L6: 0.12
A7: Potential Loyalist | B7: =Segment_Summary!D7 -> 217 | C7: =Segment_Summary!J7 -> 0.11255817 | D7: Increase frequency & lock longer validity | E7: Upgrade ₹299 -> ₹479 (56 days) and get 10GB bonus; loyalty points on every recharge | F7: P002 ₹479, P010 Entertainment ₹349 | G7: App push, SMS, Instagram Reels retargeting | H7: "Double validity, half the hassle" | I7: 3 days before validity ends | J7: Get 56 days | K7: 2nd/3rd recharge rate, plan upgrade % | L7: 0.1
A8: New Customers | B8: =Segment_Summary!D8 -> 34 | C8: =Segment_Summary!J8 -> 0.0033684287 | D8: Onboard & drive the 2nd recharge | E8: Welcome series: download app = ₹25 cashback; 2nd recharge on ₹299 gets 10GB extra | F8: P001 ₹299, P008 Student ₹666 | G8: SMS, WhatsApp onboarding flow, App in-app banners | H8: "Welcome to the fastest 5G - here's a starter gift" | I8: Day 1, 7, 21 after first recharge | J8: Activate gift | K8: App install %, 2nd recharge % | L8: 0.1
A9: Promising | B9: =Segment_Summary!D9 -> 105 | C9: =Segment_Summary!J9 -> 0.020120087 | D9: Build habit & discover value packs | E9: Try Entertainment Pack ₹349 with free OTT trial; ₹20 off via UPI | F9: P010 ₹349, P009 WFH ₹499 | G9: Instagram/YouTube Shorts, Google Discovery, App push | H9: "Binge more, pay less" (lifestyle / entertainment) | I9: Weekends & evenings, 2x per week | J9: Start streaming | K9: Pack adoption, CTR | L9: 0.08
A10: Need Attention | B10: =Segment_Summary!D10 -> 153 | C10: =Segment_Summary!J10 -> 0.065380165 | D10: Re-engage before they slip | E10: Personalised 'Just for you' - free 2GB Data Booster on next recharge (valid 72 hrs) | F10: P004 Booster ₹148, P001 ₹299 | G10: WhatsApp, SMS, Email, Facebook retargeting | H10: "We miss your streaming - here's 2GB on us" (personal, urgent) | I10: Once; reminder after 48 hrs | J10: Claim free 2GB | K10: Recharge within 7 days % | L10: 0.08
A11: About to Sleep | B11: =Segment_Summary!D11 -> 157 | C11: =Segment_Summary!J11 -> 0.034458189 | D11: Prevent lapse | E11: ₹30 OFF on ₹299 + validity-expiry alert; bonus 1GB/day for 3 days | F11: P001 ₹299, P005 Talktime ₹99 | G11: SMS, IVR/Outbound reminder, App push | H11: "Don't lose your number benefits - recharge in 1 tap" | I11: 5, 2 and 0 days before expiry | J11: Recharge in 1 tap | K11: Reactivation %, cost per reactivation | L11: 0.08
A12: At Risk | B12: =Segment_Summary!D12 -> 204 | C12: =Segment_Summary!J12 -> 0.17406746 | D12: Win-back previous good customers | E12: 20% OFF any plan for 7 days + double data on first week; satisfaction survey with ₹50 voucher | F12: P002 ₹479, P009 ₹499 | G12: WhatsApp, Email, Outbound tele-calling, Meta lookalike exclusion | H12: "Come back to better 5G - 20% off, just for you" | I12: Burst campaign over 10 days | J12: Unlock 20% off | K12: Win-back rate, survey responses | L12: 0.12
A13: Can't Lose Them | B13: =Segment_Summary!D13 -> 20 | C13: =Segment_Summary!J13 -> 0.035765001 | D13: Urgent retention of high-value lapsing customers | E13: Retention call + exclusive Annual Plan at ₹2,499 (save ₹500) + priority care & free SIM upgrade to 5G | F13: P003 Annual, P006 Family ₹999 | G13: Outbound retention desk, WhatsApp, Email, Personal SMS | H13: "You matter to us - an exclusive offer only for valued members" | I13: Within 48 hrs of flagging; 1:1 | J13: Talk to us / Claim offer | K13: Retention %, revenue saved | L13: 0.12
A14: Hibernating | B14: =Segment_Summary!D14 -> 185 | C14: =Segment_Summary!J14 -> 0.04261326 | D14: Low-cost reactivation | E14: ₹99 Talktime pack + 1GB/day free for 7 days | F14: P005 ₹99, P004 ₹148 | G14: SMS, Programmatic display, Google UAC | H14: "Your number is waiting - restart from just ₹99" | I14: Monthly | J14: Restart at ₹99 | K14: Reactivation %, CAC | L14: 0.04
A15: Lost | B15: =Segment_Summary!D15 -> 92 | C15: =Segment_Summary!J15 -> 0.0092699995 | D15: Last-chance attempt, then suppress | E15: 3 days unlimited data FREE on any recharge; if no response, move to suppression list | F15: P001 ₹299 | G15: SMS, Email (low cost only) | H15: "One last gift before we say goodbye" | I15: One campaign + 1 reminder | J15: Claim free days | K15: Response %, list hygiene | L15: 0.02
A16: Never Recharged | B16: =Segment_Summary!D16 -> 467 | C16: =Segment_Summary!J16 -> 0 | D16: Activate first recharge | E16: First recharge 50% OFF - ₹299 plan for ₹149; free SIM-activation help & KYC assistance | F16: P001 ₹299, P008 Student ₹666 | G16: SMS, WhatsApp, Google Search, Retail/store reminders | H16: "Your SIM is ready - start with 50% off" | I16: Day 1, 3, 7 sequence | J16: Activate for ₹149 | K16: First-recharge conversion % | L16: 0.04
K17: Total budget (must = 100%) | L17: =SUM(L5:L16) -> 1
A19: Channel Playbook
A20: Channel | B20: Best for segments | C20: Format | D20: Best practice
A21: WhatsApp Business | B21: Champions, Loyal, Need Attention, At Risk | C21: Rich card + 1-tap recharge button | D21: Personalise with name & plan expiry; max 2 msgs/week; opt-in only (TRAI DND compliance).
A22: App push / in-app | B22: All active segments | C22: Short push + in-app banner | D22: Trigger on validity < 3 days, low balance, data 80% used.
A23: SMS | B23: About to Sleep, Hibernating, Lost, Never Recharged | C23: 160-char with short link | D23: Register header/template on DLT; send 10am-8pm only.
A24: Instagram / Facebook | B24: Promising, Potential Loyalist, Loyal | C24: Reels, Stories, Carousel | D24: Upload segment lists as Custom Audiences; build 1% lookalikes from Champions for acquisition.
A25: YouTube / Google | B25: Promising, Never Recharged | C25: Bumper 6s, Discovery, Search | D25: Bid on 'recharge 299', 'best 5G plan' keywords; retarget site visitors.
A26: Email | B26: Champions, At Risk, Can't Lose Them | C26: HTML with offer hero | D26: Monthly usage summary + personalised offer block.
A27: Outbound call / IVR | B27: Can't Lose Them, At Risk | C27: Retention script | D27: Prioritise by Monetary score; offer escalation ladder.
A29: 30-Day Campaign Calendar
A30: Week | B30: Focus | C30: Segments | D30: Activities
A31: Week 1 | B31: Protect revenue | C31: Can't Lose Them, At Risk | D31: Retention calls, WhatsApp exclusive offers, email win-back.
A32: Week 2 | B32: Grow value | C32: Champions, Loyal, Potential Loyalist | D32: VIP rewards, postpaid upgrade, 56-day upgrade push, referral launch.
A33: Week 3 | B33: Build habit | C33: New, Promising, Need Attention | D33: Onboarding flows, Entertainment Pack Reels, free 2GB booster.
A34: Week 4 | B34: Reactivate & clean | C34: About to Sleep, Hibernating, Lost, Never Recharged | D34: Expiry reminders, ₹99 restart, first-recharge 50% off; suppress non-responders. Re-run RFM.

Sheet Ad_Prompts
A1: Image Ad Prompts - Offer Creative Assets
A2: Paste the prompt into an image generator (Midjourney, DALL-E, Ideogram, Firefly, etc.). Replace [BRAND] with your brand name/logo. Style is inspired by bold Indian telecom ads - do NOT use Airtel/Jio logos, names or trademarks in your own creatives.
A4: # | B4: Segment | C4: Asset / Placement | D4: Size / Ratio | E4: Headline | F4: Sub-copy | G4: CTA | H4: Image Generation Prompt | I4: Negative Prompt
A5: 1 | B5: Champions | C5: Instagram feed post | D5: 1080x1080 (1:1) | E5: You're a [BRAND] Champion! | F5: 10% cashback on Annual Plan ₹2,999 + 3 months free OTT | G5: Claim VIP Reward | H5: Confident young Indian professional in smart casuals holding a glowing smartphone, golden VIP badge and confetti bursting from the screen, premium black-and-gold accents over red and white background, crown icon, text 'VIP ELITE CLUB' and '₹2,999 ANNUAL - 10% CASHBACK'. Indian telecom advertisement, bold high-contrast red and white brand palette, clean modern flat-plus-3D style like leading Indian mobile network ads, large readable sans-serif typography, [BRAND] logo top-left, price burst sticker, studio lighting, ultra sharp, commercial poster quality. Text on image exactly: headline "You're a [BRAND] Champion!", sub-text "10% cashback on Annual Plan ₹2,999 + 3 months free OTT", button "Claim VIP Reward". Aspect ratio 1:1, leave safe margins for platform UI, 8k, photorealistic people, Indian context. | I5: no competitor logos, no misspelled text, no extra fingers, no blurry faces, no watermark, no clutter
A6: 2 | B6: Champions | C6: WhatsApp / Story referral | D6: 1080x1920 (9:16) | E6: Refer a friend, both get ₹100 | F6: Share the 5G love with your gang | G6: Refer Now | H6: Two Indian friends high-fiving on a city rooftop at sunset, phones in hand linked by a glowing 5G signal arc, gift boxes with '₹100' tags floating, vertical story layout with headline at top and CTA button at bottom. Indian telecom advertisement, bold high-contrast red and white brand palette, clean modern flat-plus-3D style like leading Indian mobile network ads, large readable sans-serif typography, [BRAND] logo top-left, price burst sticker, studio lighting, ultra sharp, commercial poster quality. Text on image exactly: headline "Refer a friend, both get ₹100", sub-text "Share the 5G love with your gang", button "Refer Now". Aspect ratio 9:16, leave safe margins for platform UI, 8k, photorealistic people, Indian context. | I6: no competitor logos, no misspelled text, no extra fingers, no blurry faces, no watermark, no clutter
A7: 3 | B7: Loyal Customers | C7: Facebook / Instagram carousel card | D7: 1080x1080 (1:1) | E7: Go Postpaid. 1st Month FREE | F7: Infinity ₹499 - 75GB, unlimited calls, no recharge reminders | G7: Upgrade Now | H7: Happy Indian couple on a sofa streaming cricket on a large TV and phone, floating '75GB' 3D data cloud, big '₹499' price tag sticker with 'MONTH 1 FREE' ribbon. Indian telecom advertisement, bold high-contrast red and white brand palette, clean modern flat-plus-3D style like leading Indian mobile network ads, large readable sans-serif typography, [BRAND] logo top-left, price burst sticker, studio lighting, ultra sharp, commercial poster quality. Text on image exactly: headline "Go Postpaid. 1st Month FREE", sub-text "Infinity ₹499 - 75GB, unlimited calls, no recharge reminders", button "Upgrade Now". Aspect ratio 1:1, leave safe margins for platform UI, 8k, photorealistic people, Indian context. | I7: no competitor logos, no misspelled text, no extra fingers, no blurry faces, no watermark, no clutter
A8: 4 | B8: Loyal Customers | C8: App banner Auto-Pay | D8: 1200x628 (1.91:1) | E8: Set Auto-Pay, save ₹50 every time | F8: Never miss a recharge again | G8: Enable Auto-Pay | H8: Minimal horizontal banner, 3D smartphone with UPI-style auto-pay toggle switched ON, calendar with tick marks, coins dropping into a piggy bank, headline left, product visual right. Indian telecom advertisement, bold high-contrast red and white brand palette, clean modern flat-plus-3D style like leading Indian mobile network ads, large readable sans-serif typography, [BRAND] logo top-left, price burst sticker, studio lighting, ultra sharp, commercial poster quality. Text on image exactly: headline "Set Auto-Pay, save ₹50 every time", sub-text "Never miss a recharge again", button "Enable Auto-Pay". Aspect ratio 1.91:1, leave safe margins for platform UI, 8k, photorealistic people, Indian context. | I8: no competitor logos, no misspelled text, no extra fingers, no blurry faces, no watermark, no clutter
A9: 5 | B9: Potential Loyalist | C9: Instagram Reel cover | D9: 1080x1920 (9:16) | E9: Double validity. Half the hassle. | F9: ₹479 for 56 days + 10GB bonus | G9: Get 56 Days | H9: Young Indian college student jumping mid-air with headphones, giant calendar showing '56 DAYS' splitting from '28', dynamic speed lines, bonus '10GB' badge. Indian telecom advertisement, bold high-contrast red and white brand palette, clean modern flat-plus-3D style like leading Indian mobile network ads, large readable sans-serif typography, [BRAND] logo top-left, price burst sticker, studio lighting, ultra sharp, commercial poster quality. Text on image exactly: headline "Double validity. Half the hassle.", sub-text "₹479 for 56 days + 10GB bonus", button "Get 56 Days". Aspect ratio 9:16, leave safe margins for platform UI, 8k, photorealistic people, Indian context. | I9: no competitor logos, no misspelled text, no extra fingers, no blurry faces, no watermark, no clutter
A10: 6 | B10: Potential Loyalist | C10: Display banner | D10: 300x250 / 1200x628 | E10: Upgrade & earn loyalty points | F10: Every recharge = more rewards | G10: Upgrade | H10: Smartphone screen showing a rising points meter and star badges, coins and data icons orbiting, clean white space with red and white gradient band. Indian telecom advertisement, bold high-contrast red and white brand palette, clean modern flat-plus-3D style like leading Indian mobile network ads, large readable sans-serif typography, [BRAND] logo top-left, price burst sticker, studio lighting, ultra sharp, commercial poster quality. Text on image exactly: headline "Upgrade & earn loyalty points", sub-text "Every recharge = more rewards", button "Upgrade". Aspect ratio as per size, leave safe margins for platform UI, 8k, photorealistic people, Indian context. | I10: no competitor logos, no misspelled text, no extra fingers, no blurry faces, no watermark, no clutter
A11: 7 | B11: New Customers | C11: WhatsApp welcome card | D11: 1080x1080 (1:1) | E11: Welcome to [BRAND] 5G! | F11: Download the app & get ₹25 cashback | G11: Get Starter Gift | H11: Smiling Indian family unboxing a new SIM card with a glowing gift ribbon, app icon emerging from phone screen, welcoming warm lighting, 'WELCOME GIFT ₹25' sticker. Indian telecom advertisement, bold high-contrast deep blue and white brand palette, clean modern flat-plus-3D style like leading Indian mobile network ads, large readable sans-serif typography, [BRAND] logo top-left, price burst sticker, studio lighting, ultra sharp, commercial poster quality. Text on image exactly: headline "Welcome to [BRAND] 5G!", sub-text "Download the app & get ₹25 cashback", button "Get Starter Gift". Aspect ratio 1:1, leave safe margins for platform UI, 8k, photorealistic people, Indian context. | I11: no competitor logos, no misspelled text, no extra fingers, no blurry faces, no watermark, no clutter
A12: 8 | B12: New Customers | C12: Instagram Story 2nd recharge | D12: 1080x1920 (9:16) | E12: Your 2nd recharge = 10GB FREE | F12: On ₹299 plan, this week only | G12: Recharge Now | H12: Hand holding phone with recharge success screen, big 3D '+10GB' bursting out with sparkles, timer clock 'THIS WEEK ONLY'. Indian telecom advertisement, bold high-contrast deep blue and white brand palette, clean modern flat-plus-3D style like leading Indian mobile network ads, large readable sans-serif typography, [BRAND] logo top-left, price burst sticker, studio lighting, ultra sharp, commercial poster quality. Text on image exactly: headline "Your 2nd recharge = 10GB FREE", sub-text "On ₹299 plan, this week only", button "Recharge Now". Aspect ratio 9:16, leave safe margins for platform UI, 8k, photorealistic people, Indian context. | I12: no competitor logos, no misspelled text, no extra fingers, no blurry faces, no watermark, no clutter
A13: 9 | B13: Promising | C13: YouTube / Instagram ad | D13: 1080x1080 (1:1) | E13: Binge more, pay less | F13: Entertainment Pack ₹349 with free OTT trial | G13: Start Streaming | H13: Indian teenager lying on bed with popcorn binge-watching on phone, floating generic play buttons and movie reels (no real OTT logos), cinematic purple glow mixed with deep blue and white. Indian telecom advertisement, bold high-contrast deep blue and white brand palette, clean modern flat-plus-3D style like leading Indian mobile network ads, large readable sans-serif typography, [BRAND] logo top-left, price burst sticker, studio lighting, ultra sharp, commercial poster quality. Text on image exactly: headline "Binge more, pay less", sub-text "Entertainment Pack ₹349 with free OTT trial", button "Start Streaming". Aspect ratio 1:1, leave safe margins for platform UI, 8k, photorealistic people, Indian context. | I13: no competitor logos, no misspelled text, no extra fingers, no blurry faces, no watermark, no clutter
A14: 10 | B14: Promising | C14: Google Discovery banner | D14: 1200x628 (1.91:1) | E14: Work from home at full speed | F14: WFH Pack ₹499 - 3GB/day | G14: Get WFH Pack | H14: Indian woman on a video call at a tidy home desk with laptop and phone hotspot, speedometer graphic at max, plant and natural window light. Indian telecom advertisement, bold high-contrast deep blue and white brand palette, clean modern flat-plus-3D style like leading Indian mobile network ads, large readable sans-serif typography, [BRAND] logo top-left, price burst sticker, studio lighting, ultra sharp, commercial poster quality. Text on image exactly: headline "Work from home at full speed", sub-text "WFH Pack ₹499 - 3GB/day", button "Get WFH Pack". Aspect ratio 1.91:1, leave safe margins for platform UI, 8k, photorealistic people, Indian context. | I14: no competitor logos, no misspelled text, no extra fingers, no blurry faces, no watermark, no clutter
A15: 11 | B15: Need Attention | C15: WhatsApp personalised card | D15: 1080x1080 (1:1) | E15: Hey [Name], 2GB is on us! | F15: Free Data Booster on your next recharge - 72 hrs only | G15: Claim Free 2GB | H15: Phone with a personalised notification card, giant 3D gift box opening to reveal '2GB FREE', countdown timer '72 HRS', friendly warm tone. Indian telecom advertisement, bold high-contrast deep blue and yellow brand palette, clean modern flat-plus-3D style like leading Indian mobile network ads, large readable sans-serif typography, [BRAND] logo top-left, price burst sticker, studio lighting, ultra sharp, commercial poster quality. Text on image exactly: headline "Hey [Name], 2GB is on us!", sub-text "Free Data Booster on your next recharge - 72 hrs only", button "Claim Free 2GB". Aspect ratio 1:1, leave safe margins for platform UI, 8k, photorealistic people, Indian context. | I15: no competitor logos, no misspelled text, no extra fingers, no blurry faces, no watermark, no clutter
A16: 12 | B16: Need Attention | C16: Facebook retargeting | D16: 1200x628 (1.91:1) | E16: We miss you on the fast lane | F16: Recharge today & get bonus data | G16: Recharge Now | H16: Empty racing lane with a glowing 5G tower and a phone waiting at the start line, motion blur, sense of urgency. Indian telecom advertisement, bold high-contrast deep blue and yellow brand palette, clean modern flat-plus-3D style like leading Indian mobile network ads, large readable sans-serif typography, [BRAND] logo top-left, price burst sticker, studio lighting, ultra sharp, commercial poster quality. Text on image exactly: headline "We miss you on the fast lane", sub-text "Recharge today & get bonus data", button "Recharge Now". Aspect ratio 1.91:1, leave safe margins for platform UI, 8k, photorealistic people, Indian context. | I16: no competitor logos, no misspelled text, no extra fingers, no blurry faces, no watermark, no clutter
... A28: 24 | B28: Never Recharged | C28: Student segment Story | D28: 1080x1920 (9:16) | E28: Student Plan - 84 days | F28: ₹666 with 1GB/day + unlimited calls | G28: Get Student Plan | H28: Group of Indian college students on campus steps with books and phones, doodle-style icons of books, wifi and music notes, energetic youthful colours. Indian telecom advertisement, bold high-contrast red and white brand palette, clean modern flat-plus-3D style like leading Indian mobile network ads, large readable sans-serif typography, [BRAND] logo top-left, price burst sticker, studio lighting, ultra sharp, commercial poster quality. Text on image exactly: headline "Student Plan - 84 days", sub-text "₹666 with 1GB/day + unlimited calls", button "Get Student Plan". Aspect ratio 9:16, leave safe margins for platform UI, 8k, photorealistic people, Indian context. | I28: no competitor logos, no misspelled text, no extra fingers, no blurry faces, no watermark, no clutter
A30: Creative guidelines
B31: • | C31: Keep price & offer the largest element - Indian telecom ads lead with the ₹ number.
B32: • | C32: One offer per creative; max 7 words in headline.
B33: • | C33: Use real-looking Indian people & settings (campus, family home, metro, cricket) for relatability.
B34: • | C34: Generate text-free background first if your tool misspells text, then add copy in Canva/Figma.
B35: • | C35: Add regulatory line: 'T&C apply. Offer valid for select customers. GST extra where applicable.'
B36: • | C36: A/B test 2 creatives per segment; track CTR and recharge conversion by segment list.

Sheet Raw_Customers
A1: customer_id | B1: name | C1: phone_number | D1: email | E1: city | F1: circle | G1: join_date | H1: status | J1: Source / note
A2: C000001 | B2: Raj Yadav | C2: 7080366077 | D2: rajyadav276@gmail.com | E2: Mumbai | F2: Karnataka | G2: 45960 | H2: Active | J2: customers.csv - customer master (2,000 customers).
A3: C000002 | B3: Anita Sharma | C3: 9875013010 | D3: anitasharma347@gmail.com | E3: Pune | F3: West Bengal | G3: 44884 | H3: Active
A4: C000003 | B4: Vikram Singh | C4: 8810410734 | D4: vikramsingh629@gmail.com | E4: Hyderabad | F4: UP West | G4: 44226 | H4: Active
A5: C000004 | B5: Anita Mishra | C5: 8856724922 | D5: anitamishra764@gmail.com | E5: Pune | F5: Punjab | G5: 45362 | H5: Active
A6: C000005 | B6: Rahul Patel | C6: 6356530092 | D6: rahulpatel777@gmail.com | E6: Chennai | F6: Gujarat | G6: 44616 | H6: Active
A7: C000006 | B7: Neha Mishra | C7: 9991312389 | D7: nehamishra955@gmail.com | E7: Bangalore | F7: Delhi NCR | G7: 45378 | H7: Inactive
A8: C000007 | B8: Amit Jha | C8: 8858663642 | D8: amitjha386@gmail.com | E8: Delhi | F8: Delhi NCR | G8: 44484 | H8: Active
A9: C000008 | B9: Rahul Khan | C9: 9893500427 | D9: rahulkhan153@gmail.com | E9: Bangalore | F9: UP East | G9: 44133 | H9: Active
A10: C000009 | B10: Simran Singh | C10: 7088743519 | D10: simransingh179@gmail.com | E10: Mumbai | F10: UP East | G10: 45061 | H10: Inactive
A11: C000010 | B11: Raj Reddy | C11: 9955012277 | D11: rajreddy516@gmail.com | E11: Hyderabad | F11: Punjab | G11: 44285 | H11: Active
A12: C000011 | B12: Priya Jha | C12: 9975972912 | D12: priyajha54@gmail.com | E12: Mumbai | F12: UP East | G12: 45669 | H12: Inactive
A13: C000012 | B13: Pooja Yadav | C13: 9886948633 | D13: poojayadav576@gmail.com | E13: Pune | F13: Andhra Pradesh | G13: 44879 | H13: Active
A14: C000013 | B14: Vikram Sharma | C14: 9925441311 | D14: vikramsharma878@gmail.com | E14: Mumbai | F14: Punjab | G14: 45260 | H14: Active
... A2001: C002000 | B2001: Raj Gupta | C2001: 7078140851 | D2001: rajgupta20@gmail.com | E2001: Bangalore | F2001: Karnataka | G2001: 45398 | H2001: Active

Sheet Raw_Recharges
A1: recharge_id | B1: customer_id | C1: plan_id | D1: recharge_date | E1: amount | F1: payment_mode | G1: plan_name (lookup) | I1: Source / note
A2: RB8AFC5F4 | B2: C001816 | C2: P006 | D2: 45844.947 | E2: 999 | F2: Credit Card | G2: =IFERROR(INDEX(Raw_Plans!$B$2:$B$11,MATCH(C2,Raw_Plans!$A$2:$A$11,0)),"") -> Family Infinity 999 | I2: recharges.csv - 3,000 recharge transactions (31-Jan-2025 to 31-Jan-2026). Column G is a lookup to Raw_Plans. PRIMARY SOURCE FOR R, F and M.
A3: R60C23B48 | B3: C000235 | C3: P005 | D3: 46019.947 | E3: 99 | F3: Net Banking | G3: =IFERROR(INDEX(Raw_Plans!$B$2:$B$11,MATCH(C3,Raw_Plans!$A$2:$A$11,0)),"") -> Talktime Only
A4: R99664D6E | B4: C000404 | C4: P005 | D4: 46019.947 | E4: 99 | F4: Credit Card | G4: =IFERROR(INDEX(Raw_Plans!$B$2:$B$11,MATCH(C4,Raw_Plans!$A$2:$A$11,0)),"") -> Talktime Only
A5: R3DBEEF48 | B5: C000391 | C5: P002 | D5: 45842.947 | E5: 479 | F5: Debit Card | G5: =IFERROR(INDEX(Raw_Plans!$B$2:$B$11,MATCH(C5,Raw_Plans!$A$2:$A$11,0)),"") -> Truly Unlimited
A6: RD1F9966B | B6: C001768 | C6: P010 | D6: 45745.947 | E6: 349 | F6: Net Banking | G6: =IFERROR(INDEX(Raw_Plans!$B$2:$B$11,MATCH(C6,Raw_Plans!$A$2:$A$11,0)),"") -> Entertainment Pack
A7: R73A16AEB | B7: C000365 | C7: P001 | D7: 45988.947 | E7: 299 | F7: Debit Card | G7: =IFERROR(INDEX(Raw_Plans!$B$2:$B$11,MATCH(C7,Raw_Plans!$A$2:$A$11,0)),"") -> Unlimited 5G Data
A8: R93DB0318 | B8: C001828 | C8: P003 | D8: 46050.947 | E8: 2999 | F8: Net Banking | G8: =IFERROR(INDEX(Raw_Plans!$B$2:$B$11,MATCH(C8,Raw_Plans!$A$2:$A$11,0)),"") -> Annual Plan
A9: R5B295E44 | B9: C000379 | C9: P006 | D9: 45753.947 | E9: 999 | F9: Wallet | G9: =IFERROR(INDEX(Raw_Plans!$B$2:$B$11,MATCH(C9,Raw_Plans!$A$2:$A$11,0)),"") -> Family Infinity 999
A10: RE3602B13 | B10: C001198 | C10: P009 | D10: 46029.947 | E10: 499 | F10: Net Banking | G10: =IFERROR(INDEX(Raw_Plans!$B$2:$B$11,MATCH(C10,Raw_Plans!$A$2:$A$11,0)),"") -> Work From Home
A11: R50021919 | B11: C000678 | C11: P004 | D11: 46038.947 | E11: 148 | F11: Wallet | G11: =IFERROR(INDEX(Raw_Plans!$B$2:$B$11,MATCH(C11,Raw_Plans!$A$2:$A$11,0)),"") -> Data Booster
A12: RD4CFA3F4 | B12: C001464 | C12: P006 | D12: 46001.947 | E12: 999 | F12: Net Banking | G12: =IFERROR(INDEX(Raw_Plans!$B$2:$B$11,MATCH(C12,Raw_Plans!$A$2:$A$11,0)),"") -> Family Infinity 999
A13: R41F8FBEB | B13: C001698 | C13: P007 | D13: 45769.947 | E13: 499 | F13: Debit Card | G13: =IFERROR(INDEX(Raw_Plans!$B$2:$B$11,MATCH(C13,Raw_Plans!$A$2:$A$11,0)),"") -> Infinity 499
A14: R73266695 | B14: C000390 | C14: P003 | D14: 45907.947 | E14: 2999 | F14: Credit Card | G14: =IFERROR(INDEX(Raw_Plans!$B$2:$B$11,MATCH(C14,Raw_Plans!$A$2:$A$11,0)),"") -> Annual Plan
... A3001: R13387E77 | B3001: C000016 | C3001: P008 | D3001: 45933.947 | E3001: 666 | F3001: Net Banking | G3001: =IFERROR(INDEX(Raw_Plans!$B$2:$B$11,MATCH(C3001,Raw_Plans!$A$2:$A$11,0)),"") -> Student Plan

Sheet Raw_Plans
A1: plan_id | B1: plan_name | C1: plan_type | D1: validity_days | E1: data_gb_per_day | F1: price | H1: Source / note
A2: P001 | B2: Unlimited 5G Data | C2: Prepaid | D2: 28 | E2: 2 | F2: 299 | H2: plans.csv - plan catalogue (used for plan names and offer design).
A3: P002 | B3: Truly Unlimited | C3: Prepaid | D3: 56 | E3: 1.5 | F3: 479
A4: P003 | B4: Annual Plan | C4: Prepaid | D4: 365 | E4: 2.5 | F4: 2999
A5: P004 | B5: Data Booster | C5: Prepaid | D5: 0 | E5: 15 | F5: 148
A6: P005 | B6: Talktime Only | C6: Prepaid | D6: 28 | E6: 0 | F6: 99
A7: P006 | B7: Family Infinity 999 | C7: Postpaid | D7: 30 | E7: 100 | F7: 999
A8: P007 | B8: Infinity 499 | C8: Postpaid | D8: 30 | E8: 75 | F8: 499
A9: P008 | B9: Student Plan | C9: Prepaid | D9: 84 | E9: 1 | F9: 666
A10: P009 | B10: Work From Home | C10: Prepaid | D10: 28 | E10: 3 | F10: 499
A11: P010 | B11: Entertainment Pack | C11: Prepaid | D11: 28 | E11: 1.5 | F11: 349

Sheet Raw_Subscriptions
A1: subscription_id | B1: customer_id | C1: plan_id | D1: start_date | E1: end_date | F1: status | H1: Source / note
A2: SUB9DDDE26B | B2: C001816 | C2: P006 | D2: 45844 | E2: 45900 | F2: Expired | H2: subscriptions.csv - used for 'Active Subscription' flag.
A3: SUBC7603D7B | B3: C000235 | C3: P005 | D3: 46019 | E3: 46049 | F3: Expired
A4: SUBC0CA37A2 | B4: C000404 | C4: P005 | D4: 46019 | E4: 46047 | F4: Expired
A5: SUB87146FDD | B5: C000391 | C5: P002 | D5: 45842 | E5: 46207 | F5: Active
A6: SUBED023A63 | B6: C001768 | C6: P010 | D6: 45745 | E6: 45775 | F6: Expired
A7: SUB8345C9AB | B7: C000365 | C7: P001 | D7: 45988 | E7: 46044 | F7: Expired
A8: SUBB6AD634A | B8: C001828 | C8: P003 | D8: 46050 | E8: 46134 | F8: Active
A9: SUB4DA87B15 | B9: C000379 | C9: P006 | D9: 45753 | E9: 45783 | F9: Expired
A10: SUB85A37274 | B10: C001198 | C10: P009 | D10: 46029 | E10: 46394 | F10: Active
A11: SUB6DD8ED35 | B11: C000678 | C11: P004 | D11: 46038 | E11: 46094 | F11: Active
A12: SUBCEB2EAB6 | B12: C001464 | C12: P006 | D12: 46001 | E12: 46085 | F12: Active
A13: SUB529D0AAA | B13: C001698 | C13: P007 | D13: 45769 | E13: 45853 | F13: Expired
A14: SUB7B6C8A2A | B14: C000390 | C14: P003 | D14: 45907 | E14: 45937 | F14: Expired
... A3001: SUB91F2BF70 | B3001: C000016 | C3001: P008 | D3001: 45933 | E3001: 45961 | F3001: Expired

Sheet Raw_DataUsage
A1: usage_id | B1: customer_id | C1: usage_date | D1: data_used_mb | E1: session_time_mins | G1: Source / note
A2: DU00000001 | B2: C001469 | C2: 46031 | D2: 403.12 | E2: 51 | G2: data_usage.csv - Jan-2026 sessions; used as behavioural enrichment (data GB).
A3: DU00000002 | B3: C000585 | C3: 46052 | D3: 1874.26 | E3: 15
A4: DU00000003 | B4: C001745 | C4: 46023 | D4: 881.84 | E4: 110
A5: DU00000004 | B5: C000080 | C5: 46026 | D5: 681.09 | E5: 89
A6: DU00000005 | B6: C001255 | C6: 46038 | D6: 767.76 | E6: 88
A7: DU00000006 | B7: C000575 | C7: 46027 | D7: 1600.57 | E7: 14
A8: DU00000007 | B8: C000852 | C8: 46041 | D8: 1635.16 | E8: 149
A9: DU00000008 | B9: C001286 | C9: 46050 | D9: 291.83 | E9: 64
A10: DU00000009 | B10: C001426 | C10: 46051 | D10: 728.17 | E10: 243
A11: DU00000010 | B11: C001287 | C11: 46050 | D11: 1443.21 | E11: 68
A12: DU00000011 | B12: C000121 | C12: 46039 | D12: 1378.8 | E12: 147
A13: DU00000012 | B13: C001666 | C13: 46038 | D13: 1935.83 | E13: 227
A14: DU00000013 | B14: C000510 | C14: 46053 | D14: 632.19 | E14: 82
... A5001: DU00005000 | B5001: C000842 | C5001: 46047 | D5001: 2256.43 | E5001: 119

Sheet Raw_Calls
A1: call_id | B1: customer_id | C1: receiver_phone | D1: call_duration_sec | E1: call_date | F1: call_type | H1: Source / note
A2: CALL00000001 | B2: C001537 | C2: 9993474137 | D2: 3358 | E2: 46050.424 | F2: STD | H2: call_records.csv - 28-Dec-2025 to 31-Jan-2026; used as enrichment (call minutes).
A3: CALL00000002 | B3: C000603 | C3: 9876410442 | D3: 307 | E3: 46019.418 | F3: STD
A4: CALL00000003 | B4: C000675 | C4: 8830881720 | D4: 105 | E4: 46042.481 | F4: Local
A5: CALL00000004 | B5: C000600 | C5: 6348515917 | D5: 3226 | E5: 46036.062 | F5: Roaming
A6: CALL00000005 | B6: C002000 | C6: 8850679054 | D6: 414 | E6: 46051.018 | F6: Local
A7: CALL00000006 | B7: C000300 | C7: 8896864847 | D7: 1852 | E7: 46041.689 | F7: Local
A8: CALL00000007 | B8: C000205 | C8: 8897084353 | D8: 2142 | E8: 46045.262 | F8: Local
A9: CALL00000008 | B9: C001052 | C9: 9859546031 | D9: 3325 | E9: 46048.001 | F9: Local
A10: CALL00000009 | B10: C001324 | C10: 9922509865 | D10: 601 | E10: 46027.943 | F10: Roaming
A11: CALL00000010 | B11: C001790 | C11: 8871196826 | D11: 1287 | E11: 46019.577 | F11: Roaming
A12: CALL00000011 | B12: C001290 | C12: 9873892456 | D12: 1922 | E12: 46047.925 | F12: STD
A13: CALL00000012 | B13: C001328 | C13: 7030677825 | D13: 2592 | E13: 46051.97 | F13: Roaming
A14: CALL00000013 | B14: C001548 | C14: 6391794049 | D14: 1710 | E14: 46030.895 | F14: STD
... A5001: CALL00005000 | B5001: C000849 | C5001: 9913184327 | D5001: 2860 | E5001: 46037.141 | F5001: STD
